<?xml version="1.0" encoding="utf-8"?>
<!--Transsion Top Secret-->
<!-- 
    Copyright (C) 2016 The Android Open Source Project

    Licensed under the Apache License, Version 2.0 (the "License");
    you may not use this file except in compliance with the License.
    You may obtain a copy of the License at

         http://www.apache.org/licenses/LICENSE-2.0

    Unless required by applicable law or agreed to in writing, software
    distributed under the License is distributed on an "AS IS" BASIS,
    WITHOUT WARRANTIES OR CONDITIONS OF ANY KIND, either express or implied.
    See the License for the specific language governing permissions and
    limitations under the License
   -->

<resources xmlns:android="http://schemas.android.com/apk/res/android"
    xmlns:xliff="urn:oasis:names:tc:xliff:document:1.2">
    <string name="C1" msgid="3622720549928625541">"A<xliff:g id="SEPARATOR">=</xliff:g>阿比让<xliff:g id="TIMEZONE">|Africa/Abidjan</xliff:g>|<xliff:g id="country">科特迪瓦</xliff:g><xliff:g id="lat_lon">|5.32|-4.016</xliff:g>"</string>
    <string name="C2" msgid="9073993995416728918">"A<xliff:g id="SEPARATOR">=</xliff:g>阿克拉<xliff:g id="TIMEZONE">|Africa/Accra</xliff:g>|<xliff:g id="country">加纳</xliff:g><xliff:g id="lat_lon">|5.557|-0.201</xliff:g>"</string>
    <string name="C3" msgid="5172979423931428620">"Y<xliff:g id="SEPARATOR">=</xliff:g>亚的斯亚贝巴<xliff:g id="TIMEZONE">|Africa/Addis_Ababa</xliff:g>|<xliff:g id="country">埃塞俄比亚</xliff:g><xliff:g id="lat_lon">|9|38.75</xliff:g>"</string>
    <string name="C4" msgid="4450258423854546267">"A<xliff:g id="SEPARATOR">=</xliff:g>阿尔及尔<xliff:g id="TIMEZONE">|Africa/Algiers</xliff:g>|<xliff:g id="country">阿尔及利亚</xliff:g><xliff:g id="lat_lon">|36.775|3.06</xliff:g>"</string>
    <string name="C5" msgid="8063142106679202722">"B<xliff:g id="SEPARATOR">=</xliff:g>布兰太尔<xliff:g id="TIMEZONE">|Africa/Blantyre</xliff:g>|<xliff:g id="country">马拉维</xliff:g><xliff:g id="lat_lon">|-15.786|35.004</xliff:g>"</string>
    <string name="C6" msgid="1620940469531839828">"B<xliff:g id="SEPARATOR">=</xliff:g>布拉柴维尔<xliff:g id="TIMEZONE">|Africa/Brazzaville</xliff:g>|<xliff:g id="country">刚果共和国</xliff:g><xliff:g id="lat_lon">|-4.268|15.292</xliff:g>"</string>
    <string name="C7" msgid="8450502029020824529">"K<xliff:g id="SEPARATOR">=</xliff:g>开罗<xliff:g id="TIMEZONE">|Africa/Cairo</xliff:g>|<xliff:g id="country">埃及</xliff:g><xliff:g id="lat_lon">|30.044|31.236</xliff:g>"</string>
    <string name="C8" msgid="5843391672611053116">"K<xliff:g id="SEPARATOR">=</xliff:g>卡萨布兰卡<xliff:g id="TIMEZONE">|Africa/Casablanca</xliff:g>|<xliff:g id="country">摩洛哥</xliff:g><xliff:g id="lat_lon">|33.595|-7.619</xliff:g>"</string>
    <string name="C9" msgid="2164088076645942134">"K<xliff:g id="SEPARATOR">=</xliff:g>科纳克里<xliff:g id="TIMEZONE">|Africa/Conakry</xliff:g>|<xliff:g id="country">几内亚</xliff:g><xliff:g id="lat_lon">|9.517|-13.7</xliff:g>"</string>
    <string name="C10" msgid="6275085554326816487">"D<xliff:g id="SEPARATOR">=</xliff:g>达喀尔<xliff:g id="TIMEZONE">|Africa/Dakar</xliff:g>|<xliff:g id="country">塞内加尔</xliff:g><xliff:g id="lat_lon">|14.693|-17.448</xliff:g>"</string>
    <string name="C11" msgid="8124988526568339100">"D<xliff:g id="SEPARATOR">=</xliff:g>达累斯萨拉姆<xliff:g id="TIMEZONE">|Africa/Dar_es_Salaam</xliff:g>|<xliff:g id="country">坦桑尼亚</xliff:g><xliff:g id="lat_lon">|-6.816|39.28</xliff:g>"</string>
    <string name="C12" msgid="9058858575164534385">"J<xliff:g id="SEPARATOR">=</xliff:g>吉布提<xliff:g id="TIMEZONE">|Africa/Djibouti</xliff:g>|<xliff:g id="country">吉布提</xliff:g><xliff:g id="lat_lon">|11.815|42.845</xliff:g>"</string>
    <string name="C13" msgid="1020128319695123468">"F<xliff:g id="SEPARATOR">=</xliff:g>弗里敦<xliff:g id="TIMEZONE">|Africa/Freetown</xliff:g>|<xliff:g id="country">塞拉利品</xliff:g><xliff:g id="lat_lon">|8.479|-13.268</xliff:g>"</string>
    <string name="C14" msgid="5466600602512133072">"H<xliff:g id="SEPARATOR">=</xliff:g>哈博罗内<xliff:g id="TIMEZONE">|Africa/Gaborone</xliff:g>|<xliff:g id="country">博茨瓦纳</xliff:g><xliff:g id="lat_lon">|-24.658|25.909</xliff:g>"</string>
    <string name="C15" msgid="4045696872348427594">"H<xliff:g id="SEPARATOR">=</xliff:g>哈拉雷<xliff:g id="TIMEZONE">|Africa/Harare</xliff:g>|<xliff:g id="country">津巴布韦</xliff:g><xliff:g id="lat_lon">|-17.832|31.046</xliff:g>"</string>
    <string name="C16" msgid="109844560982762747">"Y<xliff:g id="SEPARATOR">=</xliff:g>约翰内斯堡<xliff:g id="TIMEZONE">|Africa/Johannesburg</xliff:g>|<xliff:g id="country">南非</xliff:g><xliff:g id="lat_lon">|-26.205|28.05</xliff:g>"</string>
    <string name="C17" msgid="4868414442726546214">"K<xliff:g id="SEPARATOR">=</xliff:g>坎帕拉<xliff:g id="TIMEZONE">|Africa/Kampala</xliff:g>|<xliff:g id="country">乌干达</xliff:g><xliff:g id="lat_lon">|0.318|32.581</xliff:g>"</string>
    <string name="C18" msgid="7460319039497808668">"K<xliff:g id="SEPARATOR">=</xliff:g>喀土穆<xliff:g id="TIMEZONE">|Africa/Bujumbura</xliff:g>|<xliff:g id="country">苏丹</xliff:g><xliff:g id="lat_lon">|15.564|32.535</xliff:g>"</string>
    <string name="C19" msgid="3967163989179394825">"J<xliff:g id="SEPARATOR">=</xliff:g>基加利<xliff:g id="TIMEZONE">|Africa/Kigali</xliff:g>|<xliff:g id="country">卢旺达</xliff:g><xliff:g id="lat_lon">|-1.951|30.062</xliff:g>"</string>
    <string name="C20" msgid="832336979058592106">"J<xliff:g id="SEPARATOR">=</xliff:g>金沙萨<xliff:g id="TIMEZONE">|Africa/Kinshasa</xliff:g>|<xliff:g id="country">刚果民主共和国</xliff:g><xliff:g id="lat_lon">|-4.322|15.313</xliff:g>"</string>
    <string name="C21" msgid="8691772487297796331">"L<xliff:g id="SEPARATOR">=</xliff:g>拉各斯<xliff:g id="TIMEZONE">|Africa/Lagos</xliff:g>|<xliff:g id="country">尼日利亚</xliff:g><xliff:g id="lat_lon">|6.455|3.394</xliff:g>"</string>
    <string name="C22" msgid="6061916756914828881">"M<xliff:g id="SEPARATOR">=</xliff:g>马塞卢<xliff:g id="TIMEZONE">|Africa/Maseru</xliff:g>|<xliff:g id="country">菜索托</xliff:g><xliff:g id="lat_lon">|-29.31|27.478</xliff:g>"</string>
    <string name="C23" msgid="6790461017899209498">"M<xliff:g id="SEPARATOR">=</xliff:g>摩加迪沙<xliff:g id="TIMEZONE">|Africa/Mogadishu</xliff:g>|<xliff:g id="country">索马里</xliff:g><xliff:g id="lat_lon">|2.035|45.342</xliff:g>"</string>
    <string name="C24" msgid="836730985302941979">"N<xliff:g id="SEPARATOR">=</xliff:g>内罗毕<xliff:g id="TIMEZONE">|Africa/Nairobi</xliff:g>|<xliff:g id="country">肯尼亚</xliff:g><xliff:g id="lat_lon">|-1.283|36.817</xliff:g>"</string>
    <string name="C25" msgid="6439936809920816845">"S<xliff:g id="SEPARATOR">=</xliff:g>圣多美<xliff:g id="TIMEZONE">|Africa/Sao_Tome</xliff:g>|<xliff:g id="country">圣多美和普林西比</xliff:g><xliff:g id="lat_lon">|0.339|6.731</xliff:g>"</string>
    <string name="C26" msgid="3250092456144685877">"T<xliff:g id="SEPARATOR">=</xliff:g>廷巴克图<xliff:g id="TIMEZONE">|Africa/Timbuktu</xliff:g>|<xliff:g id="country">马里</xliff:g><xliff:g id="lat_lon">|16.772|-3.009</xliff:g>"</string>
    <string name="C27" msgid="851018621577780718">"D<xliff:g id="SEPARATOR">=</xliff:g>的黎波里<xliff:g id="TIMEZONE">|Africa/Tripoli</xliff:g>|<xliff:g id="country">利比亚</xliff:g><xliff:g id="lat_lon">|32.897|13.178</xliff:g>"</string>
    <string name="C28" msgid="7979767521827885833">"T<xliff:g id="SEPARATOR">=</xliff:g>突尼斯<xliff:g id="TIMEZONE">|Africa/Tunis</xliff:g>|<xliff:g id="country">突尼斯</xliff:g><xliff:g id="lat_lon">|36.8|10.186</xliff:g>"</string>
    <string name="C29" msgid="7946114495840302218">"A<xliff:g id="SEPARATOR">=</xliff:g>安克雷奇<xliff:g id="TIMEZONE">|America/Anchorage</xliff:g>|<xliff:g id="country">美国</xliff:g><xliff:g id="lat_lon">|61.216|-149.895</xliff:g>"</string>
    <string name="C31" msgid="9017443250572798257">"A<xliff:g id="SEPARATOR">=</xliff:g>阿鲁巴<xliff:g id="TIMEZONE">|America/Aruba</xliff:g>|<xliff:g id="country"></xliff:g><xliff:g id="lat_lon">|12.501|-69.962</xliff:g>"</string>
    <string name="C32" msgid="3825060534011309483">"Y<xliff:g id="SEPARATOR">=</xliff:g>亚松森<xliff:g id="TIMEZONE">|America/Asuncion</xliff:g>|<xliff:g id="country">巴拉圭</xliff:g><xliff:g id="lat_lon">|-25.28|-57.634</xliff:g>"</string>
    <string name="C33" msgid="700410369162607101">"B<xliff:g id="SEPARATOR">=</xliff:g>巴巴多斯<xliff:g id="TIMEZONE">|America/Barbados</xliff:g>|<xliff:g id="country">巴巴多斯</xliff:g><xliff:g id="lat_lon">|13.15|-59.525</xliff:g>"</string>
    <string name="C34" msgid="4247046344370912762">"B<xliff:g id="SEPARATOR">=</xliff:g>伯利兹<xliff:g id="TIMEZONE">|America/Belize</xliff:g>|<xliff:g id="country">伯利兹</xliff:g><xliff:g id="lat_lon">|16.826|-88.76</xliff:g>"</string>
    <string name="C35" msgid="2794708943743875418">"B<xliff:g id="SEPARATOR">=</xliff:g>波哥大<xliff:g id="TIMEZONE">|America/Bogota</xliff:g>|<xliff:g id="country">哥伦比亚</xliff:g><xliff:g id="lat_lon">|4.653|-74.084</xliff:g>"</string>
    <string name="C36" msgid="5404342554664613950">"B<xliff:g id="SEPARATOR">=</xliff:g>布宜诺斯艾利斯<xliff:g id="TIMEZONE">|America/Buenos_Aires</xliff:g>|<xliff:g id="country">阿根廷</xliff:g><xliff:g id="lat_lon">|-34.608|-58.437</xliff:g>"</string>
    <string name="C37" msgid="210142862572070093">"K<xliff:g id="SEPARATOR">=</xliff:g>坎昆<xliff:g id="TIMEZONE">|America/Cancun</xliff:g>|<xliff:g id="country">墨西哥</xliff:g><xliff:g id="lat_lon">|21.162|-86.851</xliff:g>"</string>
    <string name="C38" msgid="3882347315148425276">"J<xliff:g id="SEPARATOR">=</xliff:g>加拉加斯<xliff:g id="TIMEZONE">|America/Caracas</xliff:g>|<xliff:g id="country">委内瑞拉</xliff:g><xliff:g id="lat_lon">|10.506|-66.915</xliff:g>"</string>
    <string name="C39" msgid="1273212484626323439">"K<xliff:g id="SEPARATOR">=</xliff:g>开曼群岛<xliff:g id="TIMEZONE">|America/Cayman</xliff:g>|<xliff:g id="country">美国</xliff:g><xliff:g id="lat_lon">|19.542|-80.567</xliff:g>"</string>
    <string name="C40" msgid="3106173663723475314">"Z<xliff:g id="SEPARATOR">=</xliff:g>芝加哥<xliff:g id="TIMEZONE">|America/Chicago</xliff:g>|<xliff:g id="country">美国</xliff:g><xliff:g id="lat_lon">|41.876|-87.624</xliff:g>"</string>
    <string name="C42" msgid="5638414063615009004">"K<xliff:g id="SEPARATOR">=</xliff:g>库拉索<xliff:g id="TIMEZONE">|America/Curacao</xliff:g>|<xliff:g id="country">库拉索</xliff:g><xliff:g id="lat_lon">|12.118|-68.931</xliff:g>"</string>
    <string name="C43" msgid="6826097241516998181">"D<xliff:g id="SEPARATOR">=</xliff:g>道森克里克<xliff:g id="TIMEZONE">|America/Dawson_Creek</xliff:g>|<xliff:g id="country">加拿大</xliff:g><xliff:g id="lat_lon">|55.761|-120.236</xliff:g>"</string>
    <string name="C44" msgid="2779334691893631030">"D<xliff:g id="SEPARATOR">=</xliff:g>丹佛<xliff:g id="TIMEZONE">|America/Denver</xliff:g>|<xliff:g id="country">美国</xliff:g><xliff:g id="lat_lon">|39.739|-104.985</xliff:g>"</string>
    <string name="C45" msgid="8943178793317201894">"D<xliff:g id="SEPARATOR">=</xliff:g>底特律<xliff:g id="TIMEZONE">|America/Detroit</xliff:g>|<xliff:g id="country">美国</xliff:g><xliff:g id="lat_lon">|42.332|-83.047</xliff:g>"</string>
    <string name="C46" msgid="5190250990574320177">"D<xliff:g id="SEPARATOR">=</xliff:g>多米尼加<xliff:g id="TIMEZONE">|America/Dominica</xliff:g>|<xliff:g id="country"></xliff:g><xliff:g id="lat_lon">|15.424|-61.342</xliff:g>"</string>
    <string name="C47" msgid="369754396219379227">"A<xliff:g id="SEPARATOR">=</xliff:g>埃德蒙顿<xliff:g id="TIMEZONE">|America/Edmonton</xliff:g>|<xliff:g id="country">加拿大</xliff:g><xliff:g id="lat_lon">|53.535|-113.508</xliff:g>"</string>
    <string name="C48" msgid="7918902616648922410">"S<xliff:g id="SEPARATOR">=</xliff:g>萨尔瓦多<xliff:g id="TIMEZONE">|America/El_Salvador</xliff:g>|<xliff:g id="country">萨尔瓦多</xliff:g><xliff:g id="lat_lon">|13.8|-88.914</xliff:g>"</string>
    <string name="C49" msgid="6326857727742458931">"F<xliff:g id="SEPARATOR">=</xliff:g>福塔雷萨<xliff:g id="TIMEZONE">|America/Fortaleza</xliff:g>|<xliff:g id="country">巴西</xliff:g><xliff:g id="lat_lon">|-3.73|-38.522</xliff:g>"</string>
    <string name="C50" msgid="3131498820508584398">"D<xliff:g id="SEPARATOR">=</xliff:g>大特克<xliff:g id="TIMEZONE">|America/Grand_Turk</xliff:g>|<xliff:g id="country">大特克</xliff:g><xliff:g id="lat_lon">|21.468|-71.139</xliff:g>"</string>
    <string name="C51" msgid="3122278921760822414">"G<xliff:g id="SEPARATOR">=</xliff:g>格林纳达<xliff:g id="TIMEZONE">|America/Grenada</xliff:g>|<xliff:g id="country">格林纳达</xliff:g><xliff:g id="lat_lon">|12.136|-61.69</xliff:g>"</string>
    <string name="C52" msgid="7461551991724617520">"G<xliff:g id="SEPARATOR">=</xliff:g>危地马拉<xliff:g id="TIMEZONE">|America/Guatemala</xliff:g>|<xliff:g id="country"></xliff:g><xliff:g id="lat_lon">|15.687|-90.123</xliff:g>"</string>
    <string name="C53" msgid="296242785331472791">"G<xliff:g id="SEPARATOR">=</xliff:g>圭亚那<xliff:g id="TIMEZONE">|America/Guyana</xliff:g>|<xliff:g id="country">圭亚那</xliff:g><xliff:g id="lat_lon">|4.842|-58.642</xliff:g>"</string>
    <string name="C54" msgid="4045007274020361950">"H<xliff:g id="SEPARATOR">=</xliff:g>哈利法克斯<xliff:g id="TIMEZONE">|America/Halifax</xliff:g>|<xliff:g id="country">加拿大</xliff:g><xliff:g id="lat_lon">|44.867|-63.716</xliff:g>"</string>
    <string name="C55" msgid="8180186289266487770">"H<xliff:g id="SEPARATOR">=</xliff:g>哈瓦那<xliff:g id="TIMEZONE">|America/Havana</xliff:g>|<xliff:g id="country">古巴</xliff:g><xliff:g id="lat_lon">|23.135|-82.359</xliff:g>"</string>
    <string name="C56" msgid="6062281725956353553">"Y<xliff:g id="SEPARATOR">=</xliff:g>印第安纳波利斯<xliff:g id="TIMEZONE">|America/Indiana/Indianapolis</xliff:g>|<xliff:g id="country">美国</xliff:g><xliff:g id="lat_lon">|39.768|-86.158</xliff:g>"</string>
    <string name="C57" msgid="5971109906791493563">"N<xliff:g id="SEPARATOR">=</xliff:g>诺克斯<xliff:g id="TIMEZONE">|America/Indiana/Knox</xliff:g>|<xliff:g id="country">美国</xliff:g><xliff:g id="lat_lon">|48.34|-99.69</xliff:g>"</string>
    <string name="C58" msgid="7657721717096348613">"M<xliff:g id="SEPARATOR">=</xliff:g>马伦戈<xliff:g id="TIMEZONE">|America/Indiana/Marengo</xliff:g>|<xliff:g id="country">美国</xliff:g><xliff:g id="lat_lon">|32.201|-87.757</xliff:g>"</string>
    <string name="C59" msgid="2053523400941417307">"S<xliff:g id="SEPARATOR">=</xliff:g>圣彼得堡<xliff:g id="TIMEZONE">|America/Indiana/Petersburg</xliff:g>|<xliff:g id="country">美国</xliff:g><xliff:g id="lat_lon">|27.773|-82.64</xliff:g>"</string>
    <string name="C60" msgid="8112283891039465817">"T<xliff:g id="SEPARATOR">=</xliff:g>特尔城<xliff:g id="TIMEZONE">|America/Indiana/Tell_City</xliff:g>|<xliff:g id="country">美国</xliff:g><xliff:g id="lat_lon">|37.951|-86.768</xliff:g>"</string>
    <string name="C61" msgid="7778713489993559227">"W<xliff:g id="SEPARATOR">=</xliff:g>韦韦<xliff:g id="TIMEZONE">|America/Indiana/Vevay</xliff:g>|<xliff:g id="country">美国</xliff:g><xliff:g id="lat_lon">|38.748|-85.067</xliff:g>"</string>
    <string name="C62" msgid="2667958702401099683">"F<xliff:g id="SEPARATOR">=</xliff:g>樊尚<xliff:g id="TIMEZONE">|America/Indiana/Vincennes</xliff:g>|<xliff:g id="country">美国</xliff:g><xliff:g id="lat_lon">|38.678|-87.516</xliff:g>"</string>
    <string name="C63" msgid="2251274863869460838">"W<xliff:g id="SEPARATOR">=</xliff:g>威纳马克<xliff:g id="TIMEZONE">|America/Indiana/Winamac</xliff:g>|<xliff:g id="country">美国</xliff:g><xliff:g id="lat_lon">|41.051|-86.603</xliff:g>"</string>
    <string name="C64" msgid="1051183687128385699">"J<xliff:g id="SEPARATOR">=</xliff:g>金斯敦<xliff:g id="TIMEZONE">|America/Jamaica</xliff:g>|<xliff:g id="country">牙买加</xliff:g><xliff:g id="lat_lon">|17.971|-76.793</xliff:g>"</string>
    <string name="C65" msgid="4484953311341882894">"L<xliff:g id="SEPARATOR">=</xliff:g>拉巴斯<xliff:g id="TIMEZONE">|America/La_Paz</xliff:g>|<xliff:g id="country">玻利维亚</xliff:g><xliff:g id="lat_lon">|-16.496|-68.134</xliff:g>"</string>
    <string name="C66" msgid="4486852398001333122">"L<xliff:g id="SEPARATOR">=</xliff:g>利马<xliff:g id="TIMEZONE">|America/Lima</xliff:g>|<xliff:g id="country">秘鲁</xliff:g><xliff:g id="lat_lon">|-12.062|-77.037</xliff:g>"</string>
    <string name="C67" msgid="4874799181719358019">"L<xliff:g id="SEPARATOR">=</xliff:g>洛杉矶<xliff:g id="TIMEZONE">|America/Los_Angeles</xliff:g>|<xliff:g id="country">美国</xliff:g><xliff:g id="lat_lon">|34.054|-118.243</xliff:g>"</string>
    <string name="C68" msgid="5526012011469271690">"L<xliff:g id="SEPARATOR">=</xliff:g>路易维尔<xliff:g id="TIMEZONE">|America/Louisville</xliff:g>|<xliff:g id="country">美国</xliff:g><xliff:g id="lat_lon">|38.254|-85.759</xliff:g>"</string>
    <string name="C69" msgid="6147580167560875608">"M<xliff:g id="SEPARATOR">=</xliff:g>马那瓜<xliff:g id="TIMEZONE">|America/Managua</xliff:g>|<xliff:g id="country">尼加拉瓜</xliff:g><xliff:g id="lat_lon">|12.146|-86.275</xliff:g>"</string>
    <string name="C70" msgid="3277881296053225577">"M<xliff:g id="SEPARATOR">=</xliff:g>马提尼克<xliff:g id="TIMEZONE">|America/Martinique</xliff:g>|<xliff:g id="country">马提尼克</xliff:g><xliff:g id="lat_lon">|14.611|-60.962</xliff:g>"</string>
    <string name="C71" msgid="4017941126335556194">"M<xliff:g id="SEPARATOR">=</xliff:g>门多萨<xliff:g id="TIMEZONE">|America/Mendoza</xliff:g>|<xliff:g id="country">阿根廷</xliff:g><xliff:g id="lat_lon">|-34.787|-68.438</xliff:g>"</string>
    <string name="C72" msgid="3992109594245379480">"M<xliff:g id="SEPARATOR">=</xliff:g>梅特拉卡特拉<xliff:g id="TIMEZONE">|America/Metlakatla</xliff:g>|<xliff:g id="country">美国</xliff:g><xliff:g id="lat_lon">|55.119|-131.575</xliff:g>"</string>
    <string name="C73" msgid="2715229408279026929">"M<xliff:g id="SEPARATOR">=</xliff:g>墨西哥城<xliff:g id="TIMEZONE">|America/Mexico_City</xliff:g>|<xliff:g id="country">墨西哥</xliff:g><xliff:g id="lat_lon">|19.433|-99.133</xliff:g>"</string>
    <string name="C74" msgid="4308784353529592128">"M<xliff:g id="SEPARATOR">=</xliff:g>蒙特雷<xliff:g id="TIMEZONE">|America/Monterrey</xliff:g>|<xliff:g id="country">墨西哥</xliff:g><xliff:g id="lat_lon">|25.68|-100.315</xliff:g>"</string>
    <string name="C75" msgid="1026967177018172509">"M<xliff:g id="SEPARATOR">=</xliff:g>蒙得维的亚<xliff:g id="TIMEZONE">|America/Montevideo</xliff:g>|<xliff:g id="country">乌拉圭</xliff:g><xliff:g id="lat_lon">|-34.906|-56.191</xliff:g>"</string>
    <string name="C76" msgid="5677155513568462679">"M<xliff:g id="SEPARATOR">=</xliff:g>蒙特利尔<xliff:g id="TIMEZONE">|America/Montreal</xliff:g>|<xliff:g id="country">加拿大</xliff:g><xliff:g id="lat_lon">|45.503|-73.57</xliff:g>"</string>
    <string name="C77" msgid="7071675194537613715">"N<xliff:g id="SEPARATOR">=</xliff:g>拿骚<xliff:g id="TIMEZONE">|America/Nassau</xliff:g>|<xliff:g id="country">巴哈马</xliff:g><xliff:g id="lat_lon">|25.078|-77.338</xliff:g>"</string>
    <string name="C78" msgid="705452895809394827">"N<xliff:g id="SEPARATOR">=</xliff:g>纽约<xliff:g id="TIMEZONE">|America/New_York</xliff:g>|<xliff:g id="country">美国</xliff:g><xliff:g id="lat_lon">|40.713|-74.006</xliff:g>"</string>
    <string name="C79" msgid="615046244335186458">"B<xliff:g id="SEPARATOR">=</xliff:g>比尤拉<xliff:g id="TIMEZONE">|America/North_Dakota/Beulah</xliff:g>|<xliff:g id="country">美国</xliff:g><xliff:g id="lat_lon">|47.263|-101.778</xliff:g>"</string>
    <string name="C80" msgid="7462541787750301851">"S<xliff:g id="SEPARATOR">=</xliff:g>森特<xliff:g id="TIMEZONE">|America/North_Dakota/Center</xliff:g>|<xliff:g id="country">美国</xliff:g><xliff:g id="lat_lon">|47.115|-101.3</xliff:g>"</string>
    <string name="C81" msgid="5467118811364466464">"X<xliff:g id="SEPARATOR">=</xliff:g>新塞勒姆<xliff:g id="TIMEZONE">|America/North_Dakota/New_Salem</xliff:g>|<xliff:g id="country">美国</xliff:g><xliff:g id="lat_lon">|39.708|-90.848</xliff:g>"</string>
    <string name="C82" msgid="1040250446144596478">"B<xliff:g id="SEPARATOR">=</xliff:g>巴拿马<xliff:g id="TIMEZONE">|America/Panama</xliff:g>|<xliff:g id="country">巴拿马</xliff:g><xliff:g id="lat_lon">|8.56|-81.131</xliff:g>"</string>
    <string name="C83" msgid="3734366600481445363">"F<xliff:g id="SEPARATOR">=</xliff:g>菲尼克斯<xliff:g id="TIMEZONE">|America/Phoenix</xliff:g>|<xliff:g id="country">美国</xliff:g><xliff:g id="lat_lon">|33.448|-112.074</xliff:g>"</string>
    <string name="C84" msgid="2410152141185166321">"X<xliff:g id="SEPARATOR">=</xliff:g>西班牙港<xliff:g id="TIMEZONE">|America/Port_of_Spain</xliff:g>|<xliff:g id="country">特立尼达和多巴哥</xliff:g><xliff:g id="lat_lon">|10.657|-61.518</xliff:g>"</string>
    <string name="C85" msgid="2883572094139689939">"T<xliff:g id="SEPARATOR">=</xliff:g>太子港<xliff:g id="TIMEZONE">|America/Port-au-Prince</xliff:g>|<xliff:g id="country">海地</xliff:g><xliff:g id="lat_lon">|18.547|-72.34</xliff:g>"</string>
    <string name="C86" msgid="274590042868724214">"B<xliff:g id="SEPARATOR">=</xliff:g>波多黎各<xliff:g id="TIMEZONE">|America/Puerto_Rico</xliff:g>|<xliff:g id="country">美国</xliff:g><xliff:g id="lat_lon">|18.199|-66.262</xliff:g>"</string>
    <string name="C87" msgid="2866918562243248306">"S<xliff:g id="SEPARATOR">=</xliff:g>圣多明戈<xliff:g id="TIMEZONE">|America/Santo_Domingo</xliff:g>|<xliff:g id="country">多米尼加共和国</xliff:g><xliff:g id="lat_lon">|18.48|-69.942</xliff:g>"</string>
    <string name="C88" msgid="2261702707416420550">"S<xliff:g id="SEPARATOR">=</xliff:g>圣保罗<xliff:g id="TIMEZONE">|America/Sao_Paulo</xliff:g>|<xliff:g id="country">巴西</xliff:g><xliff:g id="lat_lon">|-23.551|-46.633</xliff:g>"</string>
    <string name="C89" msgid="8517952667962700432">"S<xliff:g id="SEPARATOR">=</xliff:g>圣约翰斯<xliff:g id="TIMEZONE">|America/St_Johns</xliff:g>|<xliff:g id="country">安提瓜和巴布达</xliff:g><xliff:g id="lat_lon">|17.117|-61.85</xliff:g>"</string>
    <string name="C90" msgid="1703939848190669830">"S<xliff:g id="SEPARATOR">=</xliff:g>圣基茨岛<xliff:g id="TIMEZONE">|America/St_Kitts</xliff:g>|<xliff:g id="country">圣基茨和威尼斯联邦</xliff:g><xliff:g id="lat_lon">|17.316|-62.745</xliff:g>"</string>
    <string name="C91" msgid="4438261556294969442">"S<xliff:g id="SEPARATOR">=</xliff:g>圣卢西亚<xliff:g id="TIMEZONE">|America/St_Lucia</xliff:g>|<xliff:g id="country">圣卢西亚</xliff:g><xliff:g id="lat_lon">|13.825|-60.975</xliff:g>"</string>
    <string name="C92" msgid="3717300223413621820">"S<xliff:g id="SEPARATOR">=</xliff:g>圣托马斯<xliff:g id="TIMEZONE">|America/St_Thomas</xliff:g>|<xliff:g id="country">美属维尔京群岛</xliff:g><xliff:g id="lat_lon">|49.497|3.82</xliff:g>"</string>
    <string name="C93" msgid="964552099122372664">"D<xliff:g id="SEPARATOR">=</xliff:g>蒂华纳<xliff:g id="TIMEZONE">|America/Tijuana</xliff:g>|<xliff:g id="country">墨西哥</xliff:g><xliff:g id="lat_lon">|32.501|-116.965</xliff:g>"</string>
    <string name="C94" msgid="6254783598629305021">"D<xliff:g id="SEPARATOR">=</xliff:g>多伦多<xliff:g id="TIMEZONE">|America/Toronto</xliff:g>|<xliff:g id="country">加拿大</xliff:g><xliff:g id="lat_lon">|43.653|-79.384</xliff:g>"</string>
    <string name="C95" msgid="2144206125989179089">"W<xliff:g id="SEPARATOR">=</xliff:g>温哥华<xliff:g id="TIMEZONE">|America/Vancouver</xliff:g>|<xliff:g id="country">加拿大</xliff:g><xliff:g id="lat_lon">|49.261|-123.114</xliff:g>"</string>
    <string name="C96" msgid="3995904432128369027">"W<xliff:g id="SEPARATOR">=</xliff:g>温尼伯<xliff:g id="TIMEZONE">|America/Winnipeg</xliff:g>|<xliff:g id="country">加拿大</xliff:g><xliff:g id="lat_lon">|52.089|-97.244</xliff:g>"</string>
    <string name="C97" msgid="5667595440938233073">"N<xliff:g id="SEPARATOR">=</xliff:g>南极<xliff:g id="PHONETIC">:</xliff:g><xliff:g id="TIMEZONE">|Antarctica/South_Pole</xliff:g>|<xliff:g id="country"></xliff:g><xliff:g id="lat_lon">|-90|0</xliff:g>"</string>
    <string name="C98" msgid="2067640513126652156">"L<xliff:g id="SEPARATOR">=</xliff:g>朗伊尔城<xliff:g id="TIMEZONE">|Arctic/Longyearbyen</xliff:g>|<xliff:g id="country">挪威</xliff:g><xliff:g id="lat_lon">|78.223|15.646</xliff:g>"</string>
    <string name="C99" msgid="6750041547603679548">"A<xliff:g id="SEPARATOR">=</xliff:g>阿拉木图<xliff:g id="TIMEZONE">|Asia/Almaty</xliff:g>|<xliff:g id="country">哈萨克斯坦</xliff:g><xliff:g id="lat_lon">|43.236|76.946</xliff:g>"</string>
    <string name="C100" msgid="5995329947852415813">"A<xliff:g id="SEPARATOR">=</xliff:g>安曼<xliff:g id="TIMEZONE">|Asia/Amman</xliff:g>|<xliff:g id="country">约旦</xliff:g><xliff:g id="lat_lon">|31.952|35.924</xliff:g>"</string>
    <string name="C101" msgid="5760056604239047274">"A<xliff:g id="SEPARATOR">=</xliff:g>阿纳德尔<xliff:g id="TIMEZONE">|Asia/Anadyr</xliff:g>|<xliff:g id="country">俄罗斯</xliff:g><xliff:g id="lat_lon">|64.732|177.506</xliff:g>"</string>
    <string name="C102" msgid="9000357065825182754">"A<xliff:g id="SEPARATOR">=</xliff:g>阿克套<xliff:g id="TIMEZONE">|Asia/Aqtau</xliff:g>|<xliff:g id="country">哈萨克斯坦</xliff:g><xliff:g id="lat_lon">|43.652|51.158</xliff:g>"</string>
    <string name="C103" msgid="8781982253489209791">"B<xliff:g id="SEPARATOR">=</xliff:g>巴格达<xliff:g id="TIMEZONE">|Asia/Baghdad</xliff:g>|<xliff:g id="country">伊拉克</xliff:g><xliff:g id="lat_lon">|33.302|44.379</xliff:g>"</string>
    <string name="C104" msgid="4021122575041916540">"B<xliff:g id="SEPARATOR">=</xliff:g>巴林<xliff:g id="TIMEZONE">|Asia/Bahrain</xliff:g>|<xliff:g id="country">巴林</xliff:g><xliff:g id="lat_lon">|26.155|50.534</xliff:g>"</string>
    <string name="C105" msgid="1812915124794679606">"B<xliff:g id="SEPARATOR">=</xliff:g>巴库<xliff:g id="TIMEZONE">|Asia/Baku</xliff:g>|<xliff:g id="country">阿塞拜疆</xliff:g><xliff:g id="lat_lon">|40.367|49.835</xliff:g>"</string>
    <string name="C106" msgid="1996684628612964988">"M<xliff:g id="SEPARATOR">=</xliff:g>曼谷<xliff:g id="TIMEZONE">|Asia/Bangkok</xliff:g>|<xliff:g id="country">泰国</xliff:g><xliff:g id="lat_lon">|13.825|100.622</xliff:g>"</string>
    <string name="C107" msgid="227554925153715426">"B<xliff:g id="SEPARATOR">=</xliff:g>贝鲁特<xliff:g id="TIMEZONE">|Asia/Beirut</xliff:g>|<xliff:g id="country">黎巴嫩</xliff:g><xliff:g id="lat_lon">|33.896|35.478</xliff:g>"</string>
    <string name="C108" msgid="357033582615345158">"J<xliff:g id="SEPARATOR">=</xliff:g>加尔各答<xliff:g id="TIMEZONE">|Asia/Calcutta</xliff:g>|<xliff:g id="country">印度</xliff:g><xliff:g id="lat_lon">|22.573|88.364</xliff:g>"</string>
    <string name="C109" msgid="6386566477244958752">"D<xliff:g id="SEPARATOR">=</xliff:g>大马士革<xliff:g id="TIMEZONE">|Asia/Damascus</xliff:g>|<xliff:g id="country">叙利亚</xliff:g><xliff:g id="lat_lon">|33.513|36.31</xliff:g>"</string>
    <string name="C110" msgid="1165712058024165012">"D<xliff:g id="SEPARATOR">=</xliff:g>达卡<xliff:g id="TIMEZONE">|Asia/Dhaka</xliff:g>|<xliff:g id="country">孟加拉国</xliff:g><xliff:g id="lat_lon">|23.786|90.403</xliff:g>"</string>
    <string name="C111" msgid="5895260692253797547">"D<xliff:g id="SEPARATOR">=</xliff:g>迪拜<xliff:g id="TIMEZONE">|Asia/Dubai</xliff:g>|<xliff:g id="country">阿拉伯联合茵长国</xliff:g><xliff:g id="lat_lon">|25.265|55.292</xliff:g>"</string>
    <string name="C112" msgid="1708170128253320625">"J<xliff:g id="SEPARATOR">=</xliff:g>加沙<xliff:g id="TIMEZONE">|Asia/Gaza</xliff:g>|<xliff:g id="country">巴勒斯坦</xliff:g><xliff:g id="lat_lon">|31.443|34.36</xliff:g>"</string>
    <string name="C113" msgid="8790538811134290878">"X<xliff:g id="SEPARATOR">=</xliff:g>希伯伦<xliff:g id="TIMEZONE">|Asia/Hebron</xliff:g>|<xliff:g id="country">巴勒斯坦</xliff:g><xliff:g id="lat_lon">|31.529|35.094</xliff:g>"</string>
    <string name="C114" msgid="8019764566754082688">"H<xliff:g id="SEPARATOR">=</xliff:g>胡志明市<xliff:g id="TIMEZONE">|Asia/Ho_Chi_Minh</xliff:g>|<xliff:g id="country">越南</xliff:g><xliff:g id="lat_lon">|10.772|106.698</xliff:g>"</string>
    <string name="C115" msgid="2707316842482208016">"X<xliff:g id="SEPARATOR">=</xliff:g>香港<xliff:g id="PHONETIC">:</xliff:g><xliff:g id="TIMEZONE">|Asia/Hong_Kong</xliff:g>|<xliff:g id="country">中国</xliff:g><xliff:g id="lat_lon">|22.351|114.185</xliff:g>"</string>
    <string name="C117" msgid="486537564257069933">"Y<xliff:g id="SEPARATOR">=</xliff:g>雅加达<xliff:g id="TIMEZONE">|Asia/Jakarta</xliff:g>|<xliff:g id="country">印度尼西亚</xliff:g><xliff:g id="lat_lon">|-6.175|106.827</xliff:g>"</string>
    <string name="C118" msgid="2220594023727285784">"Y<xliff:g id="SEPARATOR">=</xliff:g>耶路撒冷<xliff:g id="TIMEZONE">|Asia/Jerusalem</xliff:g>|<xliff:g id="country"></xliff:g><xliff:g id="lat_lon">|31.796|35.212</xliff:g>"</string>
    <string name="C119" msgid="7095503078924268384">"K<xliff:g id="SEPARATOR">=</xliff:g>喀布尔<xliff:g id="TIMEZONE">|Asia/Kabul</xliff:g>|<xliff:g id="country">阿富汗</xliff:g><xliff:g id="lat_lon">|34.526|69.178</xliff:g>"</string>
    <string name="C120" msgid="4759297844750994699">"K<xliff:g id="SEPARATOR">=</xliff:g>卡拉奇<xliff:g id="TIMEZONE">|Asia/Karachi</xliff:g>|<xliff:g id="country">巴基斯坦</xliff:g><xliff:g id="lat_lon">|24.855|67.021</xliff:g>"</string>
    <string name="C121" msgid="6397452077111782277">"J<xliff:g id="SEPARATOR">=</xliff:g>加德满都<xliff:g id="TIMEZONE">|Asia/Kathmandu</xliff:g>|<xliff:g id="country">尼泊尔</xliff:g><xliff:g id="lat_lon">|27.708|85.321</xliff:g>"</string>
    <string name="C122" msgid="3384658968869783693">"J<xliff:g id="SEPARATOR">=</xliff:g>吉隆坡<xliff:g id="TIMEZONE">|Asia/Kuala_Lumpur</xliff:g>|<xliff:g id="country">马来西亚</xliff:g><xliff:g id="lat_lon">|3.152|101.694</xliff:g>"</string>
    <string name="C123" msgid="2596231413860119715">"K<xliff:g id="SEPARATOR">=</xliff:g>科威特<xliff:g id="TIMEZONE">|Asia/Kuwait</xliff:g>|<xliff:g id="country">科威特</xliff:g><xliff:g id="lat_lon">|29.273|47.498</xliff:g>"</string>
    <string name="C124" msgid="7128790644999660843">"A<xliff:g id="SEPARATOR">=</xliff:g>澳门<xliff:g id="TIMEZONE">|Asia/Macau</xliff:g>|<xliff:g id="country">中国</xliff:g><xliff:g id="lat_lon">|22.176|113.551</xliff:g>"</string>
    <string name="C125" msgid="7482612453109643531">"M<xliff:g id="SEPARATOR">=</xliff:g>马尼拉<xliff:g id="TIMEZONE">|Asia/Manila</xliff:g>|<xliff:g id="country">菲律宾</xliff:g><xliff:g id="lat_lon">|14.595|120.978</xliff:g>"</string>
    <string name="C126" msgid="89594601694005714">"M<xliff:g id="SEPARATOR">=</xliff:g>马斯喀特<xliff:g id="TIMEZONE">|Asia/Muscat</xliff:g>|<xliff:g id="country">阿曼</xliff:g><xliff:g id="lat_lon">|23.588|58.383</xliff:g>"</string>
    <string name="C127" msgid="6694878912574814081">"J<xliff:g id="SEPARATOR">=</xliff:g>金边<xliff:g id="TIMEZONE">|Asia/Phnom_Penh</xliff:g>|<xliff:g id="country">束埔寨</xliff:g><xliff:g id="lat_lon">|11.568|104.922</xliff:g>"</string>
    <string name="C128" msgid="6055116591529458940">"P<xliff:g id="SEPARATOR">=</xliff:g>平壤<xliff:g id="PHONETIC">:</xliff:g><xliff:g id="TIMEZONE">|Asia/Pyongyang</xliff:g>|<xliff:g id="country">朝鲜</xliff:g><xliff:g id="lat_lon">|39.049|125.736</xliff:g>"</string>
    <string name="C130" msgid="665609990740507143">"Y<xliff:g id="SEPARATOR">=</xliff:g>仰光<xliff:g id="TIMEZONE">|Asia/Rangoon</xliff:g>|<xliff:g id="country">缅甸</xliff:g><xliff:g id="lat_lon">|16.797|96.161</xliff:g>"</string>
    <string name="C131" msgid="3395769966117356927">"L<xliff:g id="SEPARATOR">=</xliff:g>利雅得<xliff:g id="TIMEZONE">|Asia/Riyadh</xliff:g>|<xliff:g id="country">沙特阿拉伯</xliff:g><xliff:g id="lat_lon">|24.639|46.716</xliff:g>"</string>
    <string name="C133" msgid="5204810106521056060">"S<xliff:g id="SEPARATOR">=</xliff:g>首尔<xliff:g id="TIMEZONE">|Asia/Seoul</xliff:g>|<xliff:g id="country">韩国</xliff:g><xliff:g id="lat_lon">|37.567|126.978</xliff:g>"</string>
    <string name="C134" msgid="7263747916569669120">"S<xliff:g id="SEPARATOR">=</xliff:g>上海<xliff:g id="PHONETIC">:</xliff:g><xliff:g id="TIMEZONE">|Asia/Shanghai</xliff:g>|<xliff:g id="country">中国</xliff:g><xliff:g id="lat_lon">|31.232|121.469</xliff:g>"</string>
    <string name="C135" msgid="4100015019260371393">"X<xliff:g id="SEPARATOR">=</xliff:g>新加坡<xliff:g id="TIMEZONE">|Asia/Singapore</xliff:g>|<xliff:g id="country">新加坡</xliff:g><xliff:g id="lat_lon">|1.357|103.819</xliff:g>"</string>
    <string name="C136" msgid="6386033226757339839">"T<xliff:g id="SEPARATOR">=</xliff:g>台北<xliff:g id="PHONETIC">:</xliff:g><xliff:g id="TIMEZONE">|Asia/Taipei</xliff:g>|<xliff:g id="country">中国</xliff:g><xliff:g id="lat_lon">|25.038|121.564</xliff:g>"</string>
    <string name="C137" msgid="5387760734363179588">"D<xliff:g id="SEPARATOR">=</xliff:g>德黑兰<xliff:g id="TIMEZONE">|Asia/Tehran</xliff:g>|<xliff:g id="country">伊朗</xliff:g><xliff:g id="lat_lon">|35.689|51.39</xliff:g>"</string>
    <string name="C138" msgid="7193922868117846792">"T<xliff:g id="SEPARATOR">=</xliff:g>特拉维夫<xliff:g id="TIMEZONE">|Asia/Tel_Aviv</xliff:g>|<xliff:g id="country">以色列</xliff:g><xliff:g id="lat_lon">|32.085|34.782</xliff:g>"</string>
    <string name="C139" msgid="7060339477340222608">"D<xliff:g id="SEPARATOR">=</xliff:g>东京<xliff:g id="PHONETIC">:</xliff:g><xliff:g id="TIMEZONE">|Asia/Tokyo</xliff:g>|<xliff:g id="country">日本</xliff:g><xliff:g id="lat_lon">|35.683|139.759</xliff:g>"</string>
    <string name="C140" msgid="6273911458061121975">"W<xliff:g id="SEPARATOR">=</xliff:g>乌兰巴托<xliff:g id="TIMEZONE">|Asia/Ulaanbaatar</xliff:g>|<xliff:g id="country">蒙古</xliff:g><xliff:g id="lat_lon">|47.918|106.918</xliff:g>"</string>
    <string name="C141" msgid="2799340184229547409">"B<xliff:g id="SEPARATOR">=</xliff:g>百慕大<xliff:g id="TIMEZONE">|Atlantic/Bermuda</xliff:g>|<xliff:g id="country">百慕大</xliff:g><xliff:g id="lat_lon">|32.302|-64.76</xliff:g>"</string>
    <string name="C142" msgid="6015789133959684677">"J<xliff:g id="SEPARATOR">=</xliff:g>加那利<xliff:g id="TIMEZONE">|Atlantic/Canary</xliff:g>|<xliff:g id="country">西班牙</xliff:g><xliff:g id="lat_lon">|28.536|-15.749</xliff:g>"</string>
    <string name="C143" msgid="4888764215053863961">"F<xliff:g id="SEPARATOR">=</xliff:g>佛得角<xliff:g id="TIMEZONE">|Atlantic/Cape_Verde</xliff:g>|<xliff:g id="country">佛得角</xliff:g><xliff:g id="lat_lon">|16|-24.008</xliff:g>"</string>
    <string name="C144" msgid="3338105941475340049">"L<xliff:g id="SEPARATOR">=</xliff:g>雷克雅未克<xliff:g id="TIMEZONE">|Atlantic/Reykjavik</xliff:g>|<xliff:g id="country">冰岛</xliff:g><xliff:g id="lat_lon">|64.146|-21.942</xliff:g>"</string>
    <string name="C145" msgid="8684297689430494031">"S<xliff:g id="SEPARATOR">=</xliff:g>斯坦利<xliff:g id="TIMEZONE">|Atlantic/Stanley</xliff:g>|<xliff:g id="country">福克兰群岛</xliff:g><xliff:g id="lat_lon">|-51.694|-57.85</xliff:g>"</string>
    <string name="C146" msgid="843808286721172656">"A<xliff:g id="SEPARATOR">=</xliff:g>阿德莱德<xliff:g id="TIMEZONE">|Australia/Adelaide</xliff:g>|<xliff:g id="country">澳大利亚</xliff:g><xliff:g id="lat_lon">|-34.928|138.6</xliff:g>"</string>
    <string name="C147" msgid="3712535858465321034">"B<xliff:g id="SEPARATOR">=</xliff:g>布里斯班<xliff:g id="TIMEZONE">|Australia/Brisbane</xliff:g>|<xliff:g id="country">澳大利亚</xliff:g><xliff:g id="lat_lon">|-27.469|153.023</xliff:g>"</string>
    <string name="C148" msgid="7019403666599702943">"K<xliff:g id="SEPARATOR">=</xliff:g>堪培拉<xliff:g id="TIMEZONE">|Australia/Canberra</xliff:g>|<xliff:g id="country">澳大利亚</xliff:g><xliff:g id="lat_lon">|-35.298|149.101</xliff:g>"</string>
    <string name="C149" msgid="8185355499458013534">"D<xliff:g id="SEPARATOR">=</xliff:g>达尔文<xliff:g id="TIMEZONE">|Australia/Darwin</xliff:g>|<xliff:g id="country">澳大利亚</xliff:g><xliff:g id="lat_lon">|-12.46|130.841</xliff:g>"</string>
    <string name="C150" msgid="3516845880105752618">"M<xliff:g id="SEPARATOR">=</xliff:g>墨尔本<xliff:g id="TIMEZONE">|Australia/Melbourne</xliff:g>|<xliff:g id="country">澳大利亚</xliff:g><xliff:g id="lat_lon">|-37.814|144.963</xliff:g>"</string>
    <string name="C151" msgid="5576825403360541823">"X<xliff:g id="SEPARATOR">=</xliff:g>新南威尔士<xliff:g id="TIMEZONE">|Australia/NSW</xliff:g>|<xliff:g id="country">澳大利亚</xliff:g><xliff:g id="lat_lon">|-31.876|147.287</xliff:g>"</string>
    <string name="C152" msgid="7889900618915436602">"P<xliff:g id="SEPARATOR">=</xliff:g>珀斯<xliff:g id="TIMEZONE">|Australia/Perth</xliff:g>|<xliff:g id="country">溴大利亚</xliff:g><xliff:g id="lat_lon">|-31.953|115.86</xliff:g>"</string>
    <string name="C153" msgid="7506204460601953711">"K<xliff:g id="SEPARATOR">=</xliff:g>昆士兰<xliff:g id="TIMEZONE">|Australia/Queensland</xliff:g>|<xliff:g id="country">澳大利亚</xliff:g><xliff:g id="lat_lon">|-22.165|144.584</xliff:g>"</string>
    <string name="C154" msgid="1193262944948312063">"X<xliff:g id="SEPARATOR">=</xliff:g>悉尼<xliff:g id="TIMEZONE">|Australia/Sydney</xliff:g>|<xliff:g id="country">澳大利亚</xliff:g><xliff:g id="lat_lon">|-33.855|151.216</xliff:g>"</string>
    <string name="C155" msgid="7079072802229033042">"W<xliff:g id="SEPARATOR">=</xliff:g>维多利亚<xliff:g id="TIMEZONE">|Indian/Mahe</xliff:g>|<xliff:g id="country">塞舌尔</xliff:g><xliff:g id="lat_lon">|-4.624|, 55.454</xliff:g>"</string>
    <string name="C156" msgid="4003110220147338835">"N<xliff:g id="SEPARATOR">=</xliff:g>纽芬兰<xliff:g id="TIMEZONE">|Canada/Newfoundland</xliff:g>|<xliff:g id="country">加拿大</xliff:g><xliff:g id="lat_lon">|49.121|-56.696</xliff:g>"</string>
    <string name="C157" msgid="2861486997803753970">"S<xliff:g id="SEPARATOR">=</xliff:g>萨斯喀彻温<xliff:g id="TIMEZONE">|Canada/Saskatchewan</xliff:g>|<xliff:g id="country">加拿大</xliff:g><xliff:g id="lat_lon">|55.532|-106.141</xliff:g>"</string>
    <string name="C158" msgid="6882933026191056506">"F<xliff:g id="SEPARATOR">=</xliff:g>复活节岛<xliff:g id="TIMEZONE">|Chile/EasterIsland</xliff:g>|<xliff:g id="country">智利</xliff:g><xliff:g id="lat_lon">|-27.126|-109.35</xliff:g>"</string>
    <string name="C159" msgid="4128429767051043903">"A<xliff:g id="SEPARATOR">=</xliff:g>阿姆斯特丹<xliff:g id="TIMEZONE">|Europe/Amsterdam</xliff:g>|<xliff:g id="country">荷兰</xliff:g><xliff:g id="lat_lon">|52.373|4.894</xliff:g>"</string>
    <string name="C160" msgid="3488513735205092653">"A<xliff:g id="SEPARATOR">=</xliff:g>安道尔<xliff:g id="TIMEZONE">|Europe/Andorra</xliff:g>|<xliff:g id="country">安道尔</xliff:g><xliff:g id="lat_lon">|42.541|1.573</xliff:g>"</string>
    <string name="C161" msgid="7244325364130392348">"Y<xliff:g id="SEPARATOR">=</xliff:g>雅典<xliff:g id="TIMEZONE">|Europe/Athens</xliff:g>|<xliff:g id="country">希腊</xliff:g><xliff:g id="lat_lon">|37.984|23.728</xliff:g>"</string>
    <string name="C162" msgid="7484009548361072313">"B<xliff:g id="SEPARATOR">=</xliff:g>贝尔法斯特<xliff:g id="TIMEZONE">|Europe/Belfast</xliff:g>|<xliff:g id="country">英国</xliff:g><xliff:g id="lat_lon">|54.596|-5.93</xliff:g>"</string>
    <string name="C163" msgid="6106990061397073808">"B<xliff:g id="SEPARATOR">=</xliff:g>贝尔格莱德<xliff:g id="TIMEZONE">|Europe/Belgrade</xliff:g>|<xliff:g id="country">塞尔维亚</xliff:g><xliff:g id="lat_lon">|44.818|20.457</xliff:g>"</string>
    <string name="C164" msgid="3074767496771260157">"B<xliff:g id="SEPARATOR">=</xliff:g>柏林<xliff:g id="TIMEZONE">|Europe/Berlin</xliff:g>|<xliff:g id="country">德国</xliff:g><xliff:g id="lat_lon">|52.517|13.389</xliff:g>"</string>
    <string name="C165" msgid="4442005045172394762">"B<xliff:g id="SEPARATOR">=</xliff:g>布拉迪斯拉发<xliff:g id="TIMEZONE">|Europe/Bratislava</xliff:g>|<xliff:g id="country">斯洛伐克</xliff:g><xliff:g id="lat_lon">|48.152|17.109</xliff:g>"</string>
    <string name="C166" msgid="8977286721038142474">"B<xliff:g id="SEPARATOR">=</xliff:g>布鲁塞尔<xliff:g id="TIMEZONE">|Europe/Brussels</xliff:g>|<xliff:g id="country">比利时</xliff:g><xliff:g id="lat_lon">|50.847|4.352</xliff:g>"</string>
    <string name="C167" msgid="5502175796232774744">"B<xliff:g id="SEPARATOR">=</xliff:g>布加勒斯特<xliff:g id="TIMEZONE">|Europe/Bucharest</xliff:g>|<xliff:g id="country">罗马尼亚</xliff:g><xliff:g id="lat_lon">|44.436|26.103</xliff:g>"</string>
    <string name="C168" msgid="6750159439632567316">"B<xliff:g id="SEPARATOR">=</xliff:g>布达佩斯<xliff:g id="TIMEZONE">|Europe/Budapest</xliff:g>|<xliff:g id="country">匈牙利</xliff:g><xliff:g id="lat_lon">|47.498|19.04</xliff:g>"</string>
    <string name="C169" msgid="591483187800562071">"J<xliff:g id="SEPARATOR">=</xliff:g>基希讷乌<xliff:g id="TIMEZONE">|Europe/Chisinau</xliff:g>|<xliff:g id="country">摩尔多瓦</xliff:g><xliff:g id="lat_lon">|47.025|28.832</xliff:g>"</string>
    <string name="C170" msgid="157539770076958216">"G<xliff:g id="SEPARATOR">=</xliff:g>哥本哈根<xliff:g id="TIMEZONE">|Europe/Copenhagen</xliff:g>|<xliff:g id="country">丹麦</xliff:g><xliff:g id="lat_lon">|55.687|12.57</xliff:g>"</string>
    <string name="C171" msgid="4774534094571993566">"D<xliff:g id="SEPARATOR">=</xliff:g>都柏林<xliff:g id="TIMEZONE">|Europe/Dublin</xliff:g>|<xliff:g id="country">爱尔兰</xliff:g><xliff:g id="lat_lon">|53.35|-6.26</xliff:g>"</string>
    <string name="C172" msgid="6781166861618808351">"Z<xliff:g id="SEPARATOR">=</xliff:g>直布罗陀<xliff:g id="TIMEZONE">|Europe/Gibraltar</xliff:g>|<xliff:g id="country">直布罗陀</xliff:g><xliff:g id="lat_lon">|36.141|-5.354</xliff:g>"</string>
    <string name="C173" msgid="6620286361619640304">"H<xliff:g id="SEPARATOR">=</xliff:g>赫尔辛基<xliff:g id="TIMEZONE">|Europe/Helsinki</xliff:g>|<xliff:g id="country">芬兰</xliff:g><xliff:g id="lat_lon">|60.167|24.943</xliff:g>"</string>
    <string name="C174" msgid="2279016324825973473">"M<xliff:g id="SEPARATOR">=</xliff:g>马恩岛<xliff:g id="TIMEZONE">|Europe/Isle_of_Man</xliff:g>|<xliff:g id="country"></xliff:g><xliff:g id="lat_lon">|54.236|-4.515</xliff:g>"</string>
    <string name="C175" msgid="3290185117135612679">"Y<xliff:g id="SEPARATOR">=</xliff:g>伊斯坦布尔<xliff:g id="TIMEZONE">|Europe/Istanbul</xliff:g>|<xliff:g id="country">士耳其</xliff:g><xliff:g id="lat_lon">|41.01|28.965</xliff:g>"</string>
    <string name="C176" msgid="8375703098860926099">"J<xliff:g id="SEPARATOR">=</xliff:g>基辅<xliff:g id="TIMEZONE">|Europe/Kiev</xliff:g>|<xliff:g id="country">乌克兰</xliff:g><xliff:g id="lat_lon">|50.45|30.524</xliff:g>"</string>
    <string name="C177" msgid="6500868250597874838">"L<xliff:g id="SEPARATOR">=</xliff:g>里斯本<xliff:g id="TIMEZONE">|Europe/Lisbon</xliff:g>|<xliff:g id="country">葡萄牙</xliff:g><xliff:g id="lat_lon">|38.708|-9.137</xliff:g>"</string>
    <string name="C178" msgid="8805696770032311110">"L<xliff:g id="SEPARATOR">=</xliff:g>伦敦<xliff:g id="TIMEZONE">|Europe/London</xliff:g>|<xliff:g id="country">英国</xliff:g><xliff:g id="lat_lon">|51.507|-0.128</xliff:g>"</string>
    <string name="C179" msgid="3767343883668628062">"L<xliff:g id="SEPARATOR">=</xliff:g>卢森堡<xliff:g id="TIMEZONE">|Europe/Luxembourg</xliff:g>|<xliff:g id="country">卢森堡</xliff:g><xliff:g id="lat_lon">|49.816|6.13</xliff:g>"</string>
    <string name="C180" msgid="7678392789982322642">"M<xliff:g id="SEPARATOR">=</xliff:g>马德里<xliff:g id="TIMEZONE">|Europe/Madrid</xliff:g>|<xliff:g id="country">西班牙</xliff:g><xliff:g id="lat_lon">|40.417|-3.704</xliff:g>"</string>
    <string name="C181" msgid="7514462880775616081">"M<xliff:g id="SEPARATOR">=</xliff:g>马耳他<xliff:g id="TIMEZONE">|Europe/Malta</xliff:g>|<xliff:g id="country">马耳他</xliff:g><xliff:g id="lat_lon">|35.889|14.448</xliff:g>"</string>
    <string name="C182" msgid="1916950203622380579">"M<xliff:g id="SEPARATOR">=</xliff:g>明斯克<xliff:g id="TIMEZONE">|Europe/Minsk</xliff:g>|<xliff:g id="country">白俄罗斯</xliff:g><xliff:g id="lat_lon">|53.902|27.562</xliff:g>"</string>
    <string name="C183" msgid="4964892686115215073">"M<xliff:g id="SEPARATOR">=</xliff:g>摩纳哥<xliff:g id="TIMEZONE">|Europe/Monaco</xliff:g>|<xliff:g id="country">摩纳哥</xliff:g><xliff:g id="lat_lon">|43.738|7.424</xliff:g>"</string>
    <string name="C184" msgid="4848586310907586448">"M<xliff:g id="SEPARATOR">=</xliff:g>莫斯科<xliff:g id="TIMEZONE">|Europe/Moscow</xliff:g>|<xliff:g id="country">俄罗斯</xliff:g><xliff:g id="lat_lon">|55.75|37.617</xliff:g>"</string>
    <string name="C185" msgid="2598535413053285569">"A<xliff:g id="SEPARATOR">=</xliff:g>奥斯陆<xliff:g id="TIMEZONE">|Europe/Oslo</xliff:g>|<xliff:g id="country">挪威</xliff:g><xliff:g id="lat_lon">|59.913|10.739</xliff:g>"</string>
    <string name="C186" msgid="678795048839315969">"B<xliff:g id="SEPARATOR">=</xliff:g>巴黎<xliff:g id="TIMEZONE">|Europe/Paris</xliff:g>|<xliff:g id="country">法国</xliff:g><xliff:g id="lat_lon">|48.857|2.351</xliff:g>"</string>
    <string name="C187" msgid="9120486940322565800">"B<xliff:g id="SEPARATOR">=</xliff:g>布拉格<xliff:g id="TIMEZONE">|Europe/Prague</xliff:g>|<xliff:g id="country">捷克共和国</xliff:g><xliff:g id="lat_lon">|50.087|14.421</xliff:g>"</string>
    <string name="C188" msgid="6820884829000643173">"L<xliff:g id="SEPARATOR">=</xliff:g>里加<xliff:g id="TIMEZONE">|Europe/Riga</xliff:g>|<xliff:g id="country">拉脱维亚</xliff:g><xliff:g id="lat_lon">|56.949|24.105</xliff:g>"</string>
    <string name="C189" msgid="8545786001221397208">"L<xliff:g id="SEPARATOR">=</xliff:g>罗马<xliff:g id="TIMEZONE">|Europe/Rome</xliff:g>|<xliff:g id="country">意大利</xliff:g><xliff:g id="lat_lon">|41.893|12.483</xliff:g>"</string>
    <string name="C190" msgid="2822097113459737895">"S<xliff:g id="SEPARATOR">=</xliff:g>圣马力诺<xliff:g id="TIMEZONE">|Europe/San_Marino</xliff:g>|<xliff:g id="country">圣马力诺</xliff:g><xliff:g id="lat_lon">|43.946|12.458</xliff:g>"</string>
    <string name="C191" msgid="5419026915911469878">"S<xliff:g id="SEPARATOR">=</xliff:g>萨拉热窝<xliff:g id="TIMEZONE">|Europe/Sarajevo</xliff:g>|<xliff:g id="country">波斯尼亚和黑塞哥维那</xliff:g><xliff:g id="lat_lon">|43.852|18.387</xliff:g>"</string>
    <string name="C192" msgid="1416880359034236663">"X<xliff:g id="SEPARATOR">=</xliff:g>辛菲罗波尔<xliff:g id="TIMEZONE">|Europe/Simferopol</xliff:g>|<xliff:g id="country">乌克兰</xliff:g><xliff:g id="lat_lon">|44.952|34.102</xliff:g>"</string>
    <string name="C193" msgid="4639373771601474967">"S<xliff:g id="SEPARATOR">=</xliff:g>斯科普里<xliff:g id="TIMEZONE">|Europe/Skopje</xliff:g>|<xliff:g id="country">北马其顿</xliff:g><xliff:g id="lat_lon">|41.996|21.432</xliff:g>"</string>
    <string name="C194" msgid="4008819631066984591">"S<xliff:g id="SEPARATOR">=</xliff:g>索非亚<xliff:g id="TIMEZONE">|Europe/Sofia</xliff:g>|<xliff:g id="country">保加利亚</xliff:g><xliff:g id="lat_lon">|42.698|23.322</xliff:g>"</string>
    <string name="C195" msgid="6936101855361464954">"S<xliff:g id="SEPARATOR">=</xliff:g>斯德哥尔摩<xliff:g id="TIMEZONE">|Europe/Stockholm</xliff:g>|<xliff:g id="country">瑞典</xliff:g><xliff:g id="lat_lon">|59.325|18.071</xliff:g>"</string>
    <string name="C196" msgid="6845595341045260631">"T<xliff:g id="SEPARATOR">=</xliff:g>塔林<xliff:g id="TIMEZONE">|Europe/Tallinn</xliff:g>|<xliff:g id="country">爱沙尼亚</xliff:g><xliff:g id="lat_lon">|59.437|24.745</xliff:g>"</string>
    <string name="C197" msgid="2200341923401640765">"F<xliff:g id="SEPARATOR">=</xliff:g>梵帝冈<xliff:g id="TIMEZONE">|Europe/Vatican</xliff:g>|<xliff:g id="country">梵帝冈</xliff:g><xliff:g id="lat_lon">|41.903|12.453</xliff:g>"</string>
    <string name="C198" msgid="3104432830681695782">"W<xliff:g id="SEPARATOR">=</xliff:g>维也纳<xliff:g id="TIMEZONE">|Europe/Vienna</xliff:g>|<xliff:g id="country">奧地利</xliff:g><xliff:g id="lat_lon">|48.208|16.373</xliff:g>"</string>
    <string name="C199" msgid="1622823742072233091">"W<xliff:g id="SEPARATOR">=</xliff:g>维尔纽斯<xliff:g id="TIMEZONE">|Europe/Vilnius</xliff:g>|<xliff:g id="country">立陶宛</xliff:g><xliff:g id="lat_lon">|54.687|25.283</xliff:g>"</string>
    <string name="C200" msgid="6181652506383585123">"H<xliff:g id="SEPARATOR">=</xliff:g>华沙<xliff:g id="TIMEZONE">|Europe/Warsaw</xliff:g>|<xliff:g id="country">波兰</xliff:g><xliff:g id="lat_lon">|52.232|21.007</xliff:g>"</string>
    <string name="C201" msgid="5026927396527258914">"S<xliff:g id="SEPARATOR">=</xliff:g>萨格勒布<xliff:g id="TIMEZONE">|Europe/Zagreb</xliff:g>|<xliff:g id="country">克罗地亚</xliff:g><xliff:g id="lat_lon">|45.813|15.977</xliff:g>"</string>
    <string name="C202" msgid="7479245034393288391">"S<xliff:g id="SEPARATOR">=</xliff:g>苏黎世<xliff:g id="TIMEZONE">|Europe/Zurich</xliff:g>|<xliff:g id="country">瑞士</xliff:g><xliff:g id="lat_lon">|47.374|8.541</xliff:g>"</string>
    <string name="C203" msgid="1651234331866937237">"T<xliff:g id="SEPARATOR">=</xliff:g>塔那那利佛<xliff:g id="TIMEZONE">|Indian/Antananarivo</xliff:g>|<xliff:g id="country">马达加斯加</xliff:g><xliff:g id="lat_lon">|-18.91|47.526</xliff:g>"</string>
    <string name="C204" msgid="3101091022126098393">"M<xliff:g id="SEPARATOR">=</xliff:g>马尔代夫<xliff:g id="TIMEZONE">|Indian/Maldives</xliff:g>|<xliff:g id="country">马尔代夫</xliff:g><xliff:g id="lat_lon">|4.706|73.329</xliff:g>"</string>
    <string name="C205" msgid="9173530407684443044">"M<xliff:g id="SEPARATOR">=</xliff:g>毛里求斯<xliff:g id="TIMEZONE">|Indian/Mauritius</xliff:g>|<xliff:g id="country">毛里求斯</xliff:g><xliff:g id="lat_lon">|-20.276|57.57</xliff:g>"</string>
    <string name="C206" msgid="7294622489478378014">"A<xliff:g id="SEPARATOR">=</xliff:g>奥克兰<xliff:g id="TIMEZONE">|Pacific/Auckland</xliff:g>|<xliff:g id="country">美国</xliff:g><xliff:g id="lat_lon">|37.804|-122.271</xliff:g>"</string>
    <string name="C207" msgid="6369257832191627783">"F<xliff:g id="SEPARATOR">=</xliff:g>斐济<xliff:g id="TIMEZONE">|Pacific/Fiji</xliff:g>|<xliff:g id="country">斐济</xliff:g><xliff:g id="lat_lon">|-18.124|179.012</xliff:g>"</string>
    <string name="C208" msgid="1022999101729302391">"G<xliff:g id="SEPARATOR">=</xliff:g>关岛<xliff:g id="TIMEZONE">|Pacific/Guam</xliff:g>|<xliff:g id="country">关岛</xliff:g><xliff:g id="lat_lon">|13.444|144.734</xliff:g>"</string>
    <string name="C209" msgid="8326714755257287010">"T<xliff:g id="SEPARATOR">=</xliff:g>檀香山<xliff:g id="TIMEZONE">|Pacific/Honolulu</xliff:g>|<xliff:g id="country">美国</xliff:g><xliff:g id="lat_lon">|21.305|-157.856</xliff:g>"</string>
    <string name="C210" msgid="4118975261202718577">"K<xliff:g id="SEPARATOR">=</xliff:g>克里斯马斯<xliff:g id="TIMEZONE">|Pacific/Kiritimati</xliff:g>|<xliff:g id="country">基里巴斯</xliff:g><xliff:g id="lat_lon">|1.871|-157.435</xliff:g>"</string>
    <string name="C211" msgid="6016485615657297427">"N<xliff:g id="SEPARATOR">=</xliff:g>努美阿<xliff:g id="TIMEZONE">|Pacific/Noumea</xliff:g>|<xliff:g id="country">新喀里多尼亚</xliff:g><xliff:g id="lat_lon">|-22.275|166.442</xliff:g>"</string>
    <string name="C214" msgid="5230836436291372485">"A<xliff:g id="SEPARATOR">=</xliff:g>安提瓜<xliff:g id="TIMEZONE">|America/Antigua</xliff:g>|<xliff:g id="country">安提瓜和巴布达</xliff:g><xliff:g id="lat_lon">|17.078|-61.818</xliff:g>"</string>
    <string name="C215" msgid="9104600827236874744">"A<xliff:g id="SEPARATOR">=</xliff:g>奥斯汀<xliff:g id="TIMEZONE">|America/Chicago</xliff:g>|<xliff:g id="country">美国</xliff:g><xliff:g id="lat_lon">|30.271|-97.744</xliff:g>"</string>
    <string name="C216" msgid="1919768646168928906">"B<xliff:g id="SEPARATOR">=</xliff:g>波士顿<xliff:g id="TIMEZONE">|America/New_York</xliff:g>|<xliff:g id="country">美国</xliff:g><xliff:g id="lat_lon">|42.36|-71.058</xliff:g>"</string>
    <string name="C217" msgid="4879725034214879629">"K<xliff:g id="SEPARATOR">=</xliff:g>卡尔加里<xliff:g id="TIMEZONE">|America/Denver</xliff:g>|<xliff:g id="country">加拿大</xliff:g><xliff:g id="lat_lon">|51.046|-114.065</xliff:g>"</string>
    <string name="C218" msgid="5884212032925236157">"G<xliff:g id="SEPARATOR">=</xliff:g>哥伦布<xliff:g id="TIMEZONE">|America/New_York</xliff:g>|<xliff:g id="country">美国</xliff:g><xliff:g id="lat_lon">|48.904|-102.78</xliff:g>"</string>
    <string name="C219" msgid="2081823206177849440">"D<xliff:g id="SEPARATOR">=</xliff:g>达拉斯<xliff:g id="TIMEZONE">|America/Chicago</xliff:g>|<xliff:g id="country">美国</xliff:g><xliff:g id="lat_lon">|32.776|-96.797</xliff:g>"</string>
    <string name="C220" msgid="6453910991331509621">"N<xliff:g id="SEPARATOR">=</xliff:g>诺克斯维尔<xliff:g id="TIMEZONE">|America/New_York</xliff:g>|<xliff:g id="country">美国</xliff:g><xliff:g id="lat_lon">|35.96|-83.921</xliff:g>"</string>
    <string name="C221" msgid="8383807404322146544">"M<xliff:g id="SEPARATOR">=</xliff:g>孟菲斯<xliff:g id="TIMEZONE">|America/Chicago</xliff:g>|<xliff:g id="country">美国</xliff:g><xliff:g id="lat_lon">|35.149|-90.052</xliff:g>"</string>
    <string name="C222" msgid="3700668026644596138">"M<xliff:g id="SEPARATOR">=</xliff:g>迈阿密<xliff:g id="TIMEZONE">|America/New_York</xliff:g>|<xliff:g id="country">美国</xliff:g><xliff:g id="lat_lon">|25.774|-80.194</xliff:g>"</string>
    <string name="C223" msgid="221323185158028534">"M<xliff:g id="SEPARATOR">=</xliff:g>明尼阿波利斯<xliff:g id="TIMEZONE">|America/Chicago</xliff:g>|<xliff:g id="country">美国</xliff:g><xliff:g id="lat_lon">|44.977|-93.265</xliff:g>"</string>
    <string name="C224" msgid="5283127526588257314">"W<xliff:g id="SEPARATOR">=</xliff:g>渥太华<xliff:g id="TIMEZONE">|America/New_York</xliff:g>|<xliff:g id="country">加拿大</xliff:g><xliff:g id="lat_lon">|45.421|-75.69</xliff:g>"</string>
    <string name="C225" msgid="2397752406722350262">"F<xliff:g id="SEPARATOR">=</xliff:g>费城<xliff:g id="TIMEZONE">|America/New_York</xliff:g>|<xliff:g id="country">美国</xliff:g><xliff:g id="lat_lon">|39.953|-75.164</xliff:g>"</string>
    <string name="C226" msgid="9121074377966278110">"B<xliff:g id="SEPARATOR">=</xliff:g>波特兰<xliff:g id="TIMEZONE">|America/Los_Angeles</xliff:g>|<xliff:g id="country">美国</xliff:g><xliff:g id="lat_lon">|45.52|-122.674</xliff:g>"</string>
    <string name="C227" msgid="5652209241017010001">"S<xliff:g id="SEPARATOR">=</xliff:g>圣地亚哥<xliff:g id="TIMEZONE">|America/Los_Angeles</xliff:g>|<xliff:g id="country">美国</xliff:g><xliff:g id="lat_lon">|32.715|-117.162</xliff:g>"</string>
    <string name="C228" msgid="4215672329797580482">"J<xliff:g id="SEPARATOR">=</xliff:g>旧金山<xliff:g id="TIMEZONE">|America/Los_Angeles</xliff:g>|<xliff:g id="country">美国</xliff:g><xliff:g id="lat_lon">|37.779|-122.42</xliff:g>"</string>
    <string name="C229" msgid="4196312467437357156">"Y<xliff:g id="SEPARATOR">=</xliff:g>盐湖城<xliff:g id="TIMEZONE">|America/Denver</xliff:g>|<xliff:g id="country">美国</xliff:g><xliff:g id="lat_lon">|40.76|-111.887</xliff:g>"</string>
    <string name="C230" msgid="5521643115321121383">"S<xliff:g id="SEPARATOR">=</xliff:g>圣何塞<xliff:g id="TIMEZONE">|America/Costa_Rica</xliff:g>|<xliff:g id="country">哥斯达黎加</xliff:g><xliff:g id="lat_lon">|37.336|-121.891</xliff:g>"</string>
    <string name="C231" msgid="19294357270942004">"S<xliff:g id="SEPARATOR">=</xliff:g>圣萨尔瓦多<xliff:g id="TIMEZONE">|America/Guatemala</xliff:g>|<xliff:g id="country">萨尔瓦多</xliff:g><xliff:g id="lat_lon">|13.699|-89.191</xliff:g>"</string>
    <string name="C232" msgid="4714655032274833316">"X<xliff:g id="SEPARATOR">=</xliff:g>西雅图<xliff:g id="TIMEZONE">|America/Los_Angeles</xliff:g>|<xliff:g id="country">美国</xliff:g><xliff:g id="lat_lon">|47.604|-122.33</xliff:g>"</string>
    <string name="C233" msgid="7162834873553109876">"S<xliff:g id="SEPARATOR">=</xliff:g>圣路易斯<xliff:g id="TIMEZONE">|America/Chicago</xliff:g>|<xliff:g id="country">美国</xliff:g><xliff:g id="lat_lon">|38.626|-90.2</xliff:g>"</string>
    <string name="C234" msgid="8431913494781960891">"H<xliff:g id="SEPARATOR">=</xliff:g>华盛顿特区<xliff:g id="TIMEZONE">|America/New_York</xliff:g>|<xliff:g id="country">美国</xliff:g><xliff:g id="lat_lon">|38.895|-77.037</xliff:g>"</string>
    <string name="C235" msgid="8650421942456856419">"X<xliff:g id="SEPARATOR">=</xliff:g>休斯顿<xliff:g id="TIMEZONE">|America/Chicago</xliff:g>|<xliff:g id="country">美国</xliff:g><xliff:g id="lat_lon">|29.759|-95.368</xliff:g>"</string>
    <string name="C236" msgid="3687627401939103862">"S<xliff:g id="SEPARATOR">=</xliff:g>圣安东尼奥<xliff:g id="TIMEZONE">|America/Chicago</xliff:g>|<xliff:g id="country">美国</xliff:g><xliff:g id="lat_lon">|29.425|-98.495</xliff:g>"</string>
    <string name="C237" msgid="4443158977093108877">"J<xliff:g id="SEPARATOR">=</xliff:g>杰克逊维尔<xliff:g id="TIMEZONE">|America/New_York</xliff:g>|<xliff:g id="country">美国</xliff:g><xliff:g id="lat_lon">|30.332|-81.656</xliff:g>"</string>
    <string name="C238" msgid="7416660474443881822">"B<xliff:g id="SEPARATOR">=</xliff:g>巴尔的摩<xliff:g id="TIMEZONE">|America/New_York</xliff:g>|<xliff:g id="country">美国</xliff:g><xliff:g id="lat_lon">|39.291|-76.611</xliff:g>"</string>
    <string name="C239" msgid="4602819453157356596">"N<xliff:g id="SEPARATOR">=</xliff:g>纳什维尔<xliff:g id="TIMEZONE">|America/Chicago</xliff:g>|<xliff:g id="country">美国</xliff:g><xliff:g id="lat_lon">|36.162|-86.774</xliff:g>"</string>
    <string name="C240" msgid="6474976205162582188">"M<xliff:g id="SEPARATOR">=</xliff:g>密尔沃基<xliff:g id="TIMEZONE">|America/Chicago</xliff:g>|<xliff:g id="country">美国</xliff:g><xliff:g id="lat_lon">|43.035|-87.922</xliff:g>"</string>
    <string name="C241" msgid="9133192521877174743">"E<xliff:g id="SEPARATOR">=</xliff:g>俄克拉荷马城<xliff:g id="TIMEZONE">|America/Chicago</xliff:g>|<xliff:g id="country">美国</xliff:g><xliff:g id="lat_lon">|35.473|-97.517</xliff:g>"</string>
    <string name="C242" msgid="4837450655035932235">"L<xliff:g id="SEPARATOR">=</xliff:g>拉斯维加斯<xliff:g id="TIMEZONE">|America/Los_Angeles</xliff:g>|<xliff:g id="country">美国</xliff:g><xliff:g id="lat_lon">|36.167|-115.149</xliff:g>"</string>
    <string name="C243" msgid="8140503787735683522">"A<xliff:g id="SEPARATOR">=</xliff:g>阿尔伯克基<xliff:g id="TIMEZONE">|America/Denver</xliff:g>|<xliff:g id="country">美国</xliff:g><xliff:g id="lat_lon">|35.084|-106.651</xliff:g>"</string>
    <string name="C244" msgid="5425441385595386539">"T<xliff:g id="SEPARATOR">=</xliff:g>图森<xliff:g id="TIMEZONE">|MST</xliff:g>|<xliff:g id="country">美国</xliff:g><xliff:g id="lat_lon">|32.223|-110.975</xliff:g>"</string>
    <string name="C245" msgid="2117808251938937801">"S<xliff:g id="SEPARATOR">=</xliff:g>萨克拉门托<xliff:g id="TIMEZONE">|America/Los_Angeles</xliff:g>|<xliff:g id="country">美国</xliff:g><xliff:g id="lat_lon">|38.581|-121.494</xliff:g>"</string>
    <string name="C246" msgid="3092246848082816772">"Y<xliff:g id="SEPARATOR">=</xliff:g>亚特兰大<xliff:g id="TIMEZONE">|America/New_York</xliff:g>|<xliff:g id="country">美国</xliff:g><xliff:g id="lat_lon">|33.749|-84.39</xliff:g>"</string>
    <string name="C247" msgid="8206866466240263364">"K<xliff:g id="SEPARATOR">=</xliff:g>克利夫兰<xliff:g id="TIMEZONE">|America/New_York</xliff:g>|<xliff:g id="country">美国</xliff:g><xliff:g id="lat_lon">|41.505|-81.693</xliff:g>"</string>
    <string name="C248" msgid="2640187332546735575">"X<xliff:g id="SEPARATOR">=</xliff:g>新奥尔良<xliff:g id="TIMEZONE">|America/Chicago</xliff:g>|<xliff:g id="country">美国</xliff:g><xliff:g id="lat_lon">|29.976|-90.078</xliff:g>"</string>
    <string name="C249" msgid="2891345755858261436">"T<xliff:g id="SEPARATOR">=</xliff:g>坦帕<xliff:g id="TIMEZONE">|America/New_York</xliff:g>|<xliff:g id="country">美国</xliff:g><xliff:g id="lat_lon">|27.948|-82.458</xliff:g>"</string>
    <string name="C250" msgid="820338627695297018">"P<xliff:g id="SEPARATOR">=</xliff:g>匹兹堡<xliff:g id="TIMEZONE">|America/New_York</xliff:g>|<xliff:g id="country">美国</xliff:g><xliff:g id="lat_lon">|40.442|-79.99</xliff:g>"</string>
    <string name="C251" msgid="5944336862095193572">"X<xliff:g id="SEPARATOR">=</xliff:g>辛辛那提<xliff:g id="TIMEZONE">|America/New_York</xliff:g>|<xliff:g id="country">美国</xliff:g><xliff:g id="lat_lon">|39.101|-84.512</xliff:g>"</string>
    <string name="C252" msgid="4879366628092590554">"M<xliff:g id="SEPARATOR">=</xliff:g>芒廷维尤<xliff:g id="TIMEZONE">|America/Los_Angeles</xliff:g>|<xliff:g id="country">美国</xliff:g><xliff:g id="lat_lon">|37.395|-122.077</xliff:g>"</string>
    <string name="C253" msgid="131023875763265059">"L<xliff:g id="SEPARATOR">=</xliff:g>里诺<xliff:g id="TIMEZONE">|America/Los_Angeles</xliff:g>|<xliff:g id="country">美国</xliff:g><xliff:g id="lat_lon">|39.526|-119.813</xliff:g>"</string>
    <string name="C254" msgid="6114708580340716772">"H<xliff:g id="SEPARATOR">=</xliff:g>黑岩城<xliff:g id="TIMEZONE">|America/Los_Angeles</xliff:g>|<xliff:g id="country">美国</xliff:g><xliff:g id="lat_lon">|40.786|-119.206</xliff:g>"</string>
    <string name="C255" msgid="7954132426931661492">"D<xliff:g id="SEPARATOR">=</xliff:g>多哈<xliff:g id="TIMEZONE">|Asia/Riyadh</xliff:g>|<xliff:g id="country">卡塔尔</xliff:g><xliff:g id="lat_lon">|25.286|51.526</xliff:g>"</string>
    <string name="C256" msgid="4677098546257306673">"B<xliff:g id="SEPARATOR">=</xliff:g>北京<xliff:g id="PHONETIC">:</xliff:g><xliff:g id="TIMEZONE">|Asia/Shanghai</xliff:g>|<xliff:g id="country">中国</xliff:g><xliff:g id="lat_lon">|39.906|116.391</xliff:g>"</string>
    <string name="C257" msgid="6859408162854724420">"M<xliff:g id="SEPARATOR">=</xliff:g>孟买<xliff:g id="TIMEZONE">|Asia/Kolkata</xliff:g>|<xliff:g id="country">印度</xliff:g><xliff:g id="lat_lon">|19.076|72.877</xliff:g>"</string>
    <string name="C258" msgid="4883343467599097650">"X<xliff:g id="SEPARATOR">=</xliff:g>新德里<xliff:g id="TIMEZONE">|Asia/Kolkata</xliff:g>|<xliff:g id="country">印度</xliff:g><xliff:g id="lat_lon">|28.614|77.209</xliff:g>"</string>
    <string name="C259" msgid="5562442240689501324">"D<xliff:g id="SEPARATOR">=</xliff:g>大阪<xliff:g id="PHONETIC">:</xliff:g><xliff:g id="TIMEZONE">|Asia/Tokyo</xliff:g>|<xliff:g id="country">日本</xliff:g><xliff:g id="lat_lon">|34.702|135.496</xliff:g>"</string>
    <string name="C260" msgid="8364102554400427814">"L<xliff:g id="SEPARATOR">=</xliff:g>拉合尔<xliff:g id="TIMEZONE">|Asia/Karachi</xliff:g>|<xliff:g id="country">巴基斯坦</xliff:g><xliff:g id="lat_lon">|31.566|74.314</xliff:g>"</string>
    <string name="C261" msgid="4120312655526126931">"S<xliff:g id="SEPARATOR">=</xliff:g>萨那<xliff:g id="TIMEZONE">|Asia/Riyadh</xliff:g>|<xliff:g id="country">也门</xliff:g><xliff:g id="lat_lon">|15.354|44.206</xliff:g>"</string>
    <string name="C262" msgid="5548180151889833">"B<xliff:g id="SEPARATOR">=</xliff:g>巴塞罗那<xliff:g id="TIMEZONE">|Europe/Madrid</xliff:g>|<xliff:g id="country">西班牙</xliff:g><xliff:g id="lat_lon">|41.383|2.177</xliff:g>"</string>
    <string name="C263" msgid="2667061188896159784">"M<xliff:g id="SEPARATOR">=</xliff:g>慕尼黑<xliff:g id="TIMEZONE">|Europe/Berlin</xliff:g>|<xliff:g id="country">德国</xliff:g><xliff:g id="lat_lon">|48.137|11.575</xliff:g>"</string>
    <string name="C264" msgid="2183960913782375290">"M<xliff:g id="SEPARATOR">=</xliff:g>米兰<xliff:g id="TIMEZONE">|Europe/Rome</xliff:g>|<xliff:g id="country">意大利</xliff:g><xliff:g id="lat_lon">|45.464|9.19</xliff:g>"</string>
    <string name="C265" msgid="7302072801871420825">"F<xliff:g id="SEPARATOR">=</xliff:g>法兰克福<xliff:g id="TIMEZONE">|Europe/Berlin</xliff:g>|<xliff:g id="country">德国</xliff:g><xliff:g id="lat_lon">|50.111|8.682</xliff:g>"</string>
    <string name="C266" msgid="2043638131940526010">"H<xliff:g id="SEPARATOR">=</xliff:g>河内<xliff:g id="TIMEZONE">|Asia/Bangkok</xliff:g>|<xliff:g id="country">越南</xliff:g><xliff:g id="lat_lon">|21.029|105.854</xliff:g>"</string>
    <string name="C267" msgid="2210484655793571387">"A<xliff:g id="SEPARATOR">=</xliff:g>安卡拉<xliff:g id="TIMEZONE">|Europe/Istanbul</xliff:g>|<xliff:g id="country">土耳其</xliff:g><xliff:g id="lat_lon">|39.921|32.854</xliff:g>"</string>
    <string name="C268" msgid="263106973500029909">"B<xliff:g id="SEPARATOR">=</xliff:g>班加罗尔<xliff:g id="TIMEZONE">|Asia/Kolkata</xliff:g>|<xliff:g id="country">印度</xliff:g><xliff:g id="lat_lon">|12.979|77.591</xliff:g>"</string>
    <string name="C269" msgid="6541694468583591229">"B<xliff:g id="SEPARATOR">=</xliff:g>巴西利亚<xliff:g id="TIMEZONE">|America/Sao_Paulo</xliff:g>|<xliff:g id="country">巴西</xliff:g><xliff:g id="lat_lon">|-15.793|-47.882</xliff:g>"</string>
    <string name="C270" msgid="1314079881051130603">"K<xliff:g id="SEPARATOR">=</xliff:g>开普敦<xliff:g id="TIMEZONE">|Africa/Johannesburg</xliff:g>|<xliff:g id="country">南非</xliff:g><xliff:g id="lat_lon">|-33.929|18.417</xliff:g>"</string>
    <string name="C271" msgid="8640235215580011665">"Y<xliff:g id="SEPARATOR">=</xliff:g>伊斯兰堡<xliff:g id="TIMEZONE">|Asia/Karachi</xliff:g>|<xliff:g id="country">巴基斯坦</xliff:g><xliff:g id="lat_lon">|33.694|73.065</xliff:g>"</string>
    <string name="C272" msgid="1609536549681428971">"L<xliff:g id="SEPARATOR">=</xliff:g>里约热内卢<xliff:g id="TIMEZONE">|America/Sao_Paulo</xliff:g>|<xliff:g id="country">巴西</xliff:g><xliff:g id="lat_lon">|-22.911|-43.209</xliff:g>"</string>
    <string name="C273" msgid="7079941149646181981">"A<xliff:g id="SEPARATOR">=</xliff:g>安娜堡<xliff:g id="TIMEZONE">|America/Detroit</xliff:g>|<xliff:g id="country">美国</xliff:g><xliff:g id="lat_lon">|42.268|-83.731</xliff:g>"</string>
    <string name="C274" msgid="8459573593923702400">"B<xliff:g id="SEPARATOR">=</xliff:g>波尔得<xliff:g id="TIMEZONE">|America/Denver</xliff:g>|<xliff:g id="country">美国</xliff:g><xliff:g id="lat_lon">|40.015|-105.271</xliff:g>"</string>
    <string name="C275" msgid="6089570009772695384">"J<xliff:g id="SEPARATOR">=</xliff:g>剑桥<xliff:g id="TIMEZONE">|America/New_York</xliff:g>|<xliff:g id="country">美国</xliff:g><xliff:g id="lat_lon">|52.206|0.119</xliff:g>"</string>
    <string name="C276" msgid="8770778158932656740">"K<xliff:g id="SEPARATOR">=</xliff:g>柯克兰<xliff:g id="TIMEZONE">|America/Los_Angeles</xliff:g>|<xliff:g id="country">美国</xliff:g><xliff:g id="lat_lon">|47.686|-122.192</xliff:g>"</string>
    <string name="C277" msgid="3027642546928363284">"M<xliff:g id="SEPARATOR">=</xliff:g>麦迪逊<xliff:g id="TIMEZONE">|America/Chicago</xliff:g>|<xliff:g id="country">美国</xliff:g><xliff:g id="lat_lon">|43.075|-89.384</xliff:g>"</string>
    <string name="C278" msgid="2380762577096499707">"G<xliff:g id="SEPARATOR">=</xliff:g>广州<xliff:g id="PHONETIC">:</xliff:g><xliff:g id="TIMEZONE">|Asia/Shanghai</xliff:g>|<xliff:g id="country">中国</xliff:g><xliff:g id="lat_lon">|23.13|113.259</xliff:g>"</string>
    <string name="C279" msgid="8894272318704876379">"H<xliff:g id="SEPARATOR">=</xliff:g>海得拉巴<xliff:g id="TIMEZONE">|Asia/Kolkata</xliff:g>|<xliff:g id="country">印度</xliff:g><xliff:g id="lat_lon">|17.361|78.474</xliff:g>"</string>
    <string name="C280" msgid="7678401703785036372">"L<xliff:g id="SEPARATOR">=</xliff:g>雷斯顿<xliff:g id="TIMEZONE">|America/New_York</xliff:g>|<xliff:g id="country">美国</xliff:g><xliff:g id="lat_lon">|38.958|-77.358</xliff:g>"</string>
    <string name="C281" msgid="8023528134904066052">"B<xliff:g id="SEPARATOR">=</xliff:g>贝洛奥里藏特<xliff:g id="TIMEZONE">|America/Sao_Paulo</xliff:g>|<xliff:g id="country">巴西</xliff:g><xliff:g id="lat_lon">|-19.923|-43.945</xliff:g>"</string>
    <string name="C282" msgid="6695477038758559199">"S<xliff:g id="SEPARATOR">=</xliff:g>圣地亚哥<xliff:g id="TIMEZONE">|America/Santiago</xliff:g>|<xliff:g id="country">智利</xliff:g><xliff:g id="lat_lon">|-33.438|-70.65</xliff:g>"</string>
    <string name="C283" msgid="7769787200879321206">"M<xliff:g id="SEPARATOR">=</xliff:g>蒙罗维亚<xliff:g id="TIMEZONE">|Africa/Monrovia</xliff:g>|<xliff:g id="country">利比里亚</xliff:g><xliff:g id="lat_lon">|6.328|-10.798</xliff:g>"</string>
    <string name="C284" msgid="6968458422900478829">"K<xliff:g id="SEPARATOR">=</xliff:g>科伦坡<xliff:g id="TIMEZONE">|Asia/Colombo</xliff:g>|<xliff:g id="country">斯里兰卡</xliff:g><xliff:g id="lat_lon">|6.939|79.854</xliff:g>"</string>
    <string name="C285" msgid="1141404871109476705">"Q<xliff:g id="SEPARATOR">=</xliff:g>奇瓦瓦<xliff:g id="TIMEZONE">|America/Chihuahua</xliff:g>|<xliff:g id="country">墨西哥</xliff:g><xliff:g id="lat_lon">|28.5|-106</xliff:g>"</string>
    <string name="C286" msgid="4996225818359904740">"S<xliff:g id="SEPARATOR">=</xliff:g>萨尔瓦多<xliff:g id="TIMEZONE">|America/Sao_Paulo</xliff:g>|<xliff:g id="country">巴西</xliff:g><xliff:g id="lat_lon">|-12.973|-38.502</xliff:g>"</string>
    <string name="C287" msgid="1988559263618010310">"G<xliff:g id="SEPARATOR">=</xliff:g>古尔冈<xliff:g id="TIMEZONE">|Asia/Kolkata</xliff:g>|<xliff:g id="country">印度</xliff:g><xliff:g id="lat_lon">|28.428|77.003</xliff:g>"</string>
    <string name="C288" msgid="852288766460325989">"M<xliff:g id="SEPARATOR">=</xliff:g>曼彻斯特<xliff:g id="TIMEZONE">|Europe/London</xliff:g>|<xliff:g id="country">英国</xliff:g><xliff:g id="lat_lon">|53.479|-2.245</xliff:g>"</string>
    <string name="C290" msgid="9191944922972784727">"S<xliff:g id="SEPARATOR">=</xliff:g>圣彼得堡<xliff:g id="TIMEZONE">|Europe/Moscow</xliff:g>|<xliff:g id="country">俄罗斯</xliff:g><xliff:g id="lat_lon">|59.939|30.316</xliff:g>"</string>
    <string name="C291" msgid="4662360206594986867">"K<xliff:g id="SEPARATOR">=</xliff:g>克拉科夫<xliff:g id="TIMEZONE">|Europe/Warsaw</xliff:g>|<xliff:g id="country">波兰</xliff:g><xliff:g id="lat_lon">|50.062|19.937</xliff:g>"</string>
    <string name="C292" msgid="3704362015612990315">"F<xliff:g id="SEPARATOR">=</xliff:g>弗罗茨瓦夫<xliff:g id="TIMEZONE">|Europe/Warsaw</xliff:g>|<xliff:g id="country">波兰</xliff:g><xliff:g id="lat_lon">|51.109|17.033</xliff:g>"</string>
    <string name="C293" msgid="3807981967850386200">"H<xliff:g id="SEPARATOR">=</xliff:g>汉堡<xliff:g id="TIMEZONE">|Europe/Berlin</xliff:g>|<xliff:g id="country">德国</xliff:g><xliff:g id="lat_lon">|53.55|10.001</xliff:g>"</string>
    <string name="C294" msgid="2800056634746552933">"A<xliff:g id="SEPARATOR">=</xliff:g>奥卢<xliff:g id="TIMEZONE">|Europe/Bucharest</xliff:g>|<xliff:g id="country">芬兰</xliff:g><xliff:g id="lat_lon">|65.012|25.472</xliff:g>"</string>
    <string name="C295" msgid="7855357204471157922">"H<xliff:g id="SEPARATOR">=</xliff:g>海法<xliff:g id="TIMEZONE">|Asia/Jerusalem</xliff:g>|<xliff:g id="country">以色列</xliff:g><xliff:g id="lat_lon">|32.819|34.998</xliff:g>"</string>
    <string name="C296" msgid="2834361512883853579">"S<xliff:g id="SEPARATOR">=</xliff:g>圣胡安<xliff:g id="TIMEZONE">|America/Puerto_Rico</xliff:g>|<xliff:g id="country"></xliff:g><xliff:g id="lat_lon">|18.465|-66.117</xliff:g>"</string>
    <string name="C297" msgid="5314407834713913608">"T<xliff:g id="SEPARATOR">=</xliff:g>特古西加尔巴<xliff:g id="TIMEZONE">|America/Tegucigalpa</xliff:g>|<xliff:g id="country">洪都拉斯</xliff:g><xliff:g id="lat_lon">|14.106|-87.205</xliff:g>"</string>
    <string name="C298" msgid="4186340979527221275">"P<xliff:g id="SEPARATOR">=</xliff:g>帕拉马里博<xliff:g id="TIMEZONE">|America/Paramaribo</xliff:g>|<xliff:g id="country">苏里南</xliff:g><xliff:g id="lat_lon">|5.825|-55.17</xliff:g>"</string>
    <string name="C299" msgid="5688169950851674667">"J<xliff:g id="SEPARATOR">=</xliff:g>基多<xliff:g id="TIMEZONE">|America/Panama</xliff:g>|<xliff:g id="country">厄瓜多尔</xliff:g><xliff:g id="lat_lon">|-0.22|-78.512</xliff:g>"</string>
    <string name="C300" msgid="7351753589989414696">"L<xliff:g id="SEPARATOR">=</xliff:g>卢布尔雅那<xliff:g id="TIMEZONE">|Europe/Ljubljana</xliff:g>|<xliff:g id="country">斯洛文尼亚</xliff:g><xliff:g id="lat_lon">|46.05|14.507</xliff:g>"</string>
    <string name="C301" msgid="9089921329206815602">"A<xliff:g id="SEPARATOR">=</xliff:g>阿什哈巴德<xliff:g id="TIMEZONE">|Asia/Ashgabat</xliff:g>|<xliff:g id="country">土库曼斯坦</xliff:g><xliff:g id="lat_lon">|37.94|58.382</xliff:g>"</string>
    <string name="C302" msgid="6471051311513517449">"A<xliff:g id="SEPARATOR">=</xliff:g>阿斯马拉<xliff:g id="TIMEZONE">|Africa/Asmara</xliff:g>|<xliff:g id="country">厄立特里亚</xliff:g><xliff:g id="lat_lon">|15.339|38.933</xliff:g>"</string>
    <string name="C303" msgid="6208957436062127281">"S<xliff:g id="SEPARATOR">=</xliff:g>斯里巴加湾<xliff:g id="TIMEZONE">|Asia/Brunei</xliff:g>|<xliff:g id="country">文莱</xliff:g><xliff:g id="lat_lon">|4.89|114.942</xliff:g>"</string>
    <string name="C304" msgid="7757188637892125245">"B<xliff:g id="SEPARATOR">=</xliff:g>班吉<xliff:g id="TIMEZONE">|Africa/Bangui</xliff:g>|<xliff:g id="country">中非共和国</xliff:g><xliff:g id="lat_lon">|4.391|18.551</xliff:g>"</string>
    <string name="C305" msgid="5538312768539249335">"B<xliff:g id="SEPARATOR">=</xliff:g>班珠尔<xliff:g id="TIMEZONE">|Africa/Banjul</xliff:g>|<xliff:g id="country">冈比亚</xliff:g><xliff:g id="lat_lon">|13.455|-16.576</xliff:g>"</string>
    <string name="C306" msgid="6400938736119754675">"B<xliff:g id="SEPARATOR">=</xliff:g>比什凯克<xliff:g id="TIMEZONE">|Asia/Bishkek</xliff:g>|<xliff:g id="country">吉尔吉斯斯坦</xliff:g><xliff:g id="lat_lon">|42.877|74.607</xliff:g>"</string>
    <string name="C307" msgid="1169132195117591472">"B<xliff:g id="SEPARATOR">=</xliff:g>比绍<xliff:g id="TIMEZONE">|Africa/Bissau</xliff:g>|<xliff:g id="country">几内亚比绍</xliff:g><xliff:g id="lat_lon">|11.861|-15.583</xliff:g>"</string>
    <string name="C308" msgid="7704965635342439141">"B<xliff:g id="SEPARATOR">=</xliff:g>布琼布拉<xliff:g id="TIMEZONE">|Africa/Bujumbura</xliff:g>|<xliff:g id="country">布隆迪</xliff:g><xliff:g id="lat_lon">|-3.364|29.368</xliff:g>"</string>
    <string name="C309" msgid="1522235235310763925">"D<xliff:g id="SEPARATOR">=</xliff:g>帝力<xliff:g id="TIMEZONE">|Asia/Dili</xliff:g>|<xliff:g id="country">东帝汶</xliff:g><xliff:g id="lat_lon">|-8.554|125.578</xliff:g>"</string>
    <string name="C310" msgid="8666508463588411257">"D<xliff:g id="SEPARATOR">=</xliff:g>杜尚别<xliff:g id="TIMEZONE">|Asia/Dushanbe</xliff:g>|<xliff:g id="country">塔吉克斯坦</xliff:g><xliff:g id="lat_lon">|38.543|68.815</xliff:g>"</string>
    <string name="C311" msgid="5940486195605635031">"F<xliff:g id="SEPARATOR">=</xliff:g>富纳富提<xliff:g id="TIMEZONE">|Pacific/Funafuti</xliff:g>|<xliff:g id="country"></xliff:g><xliff:g id="lat_lon">|-8.52|179.198</xliff:g>"</string>
    <string name="C312" msgid="1714210141256903683">"G<xliff:g id="SEPARATOR">=</xliff:g>瓜达尔卡纳尔岛<xliff:g id="TIMEZONE">|Pacific/Guadalcanal</xliff:g>|<xliff:g id="country"></xliff:g><xliff:g id="lat_lon">|-9.67|160.078</xliff:g>"</string>
    <string name="C313" msgid="8390229571948311411">"Z<xliff:g id="SEPARATOR">=</xliff:g>朱巴<xliff:g id="TIMEZONE">|Africa/Juba</xliff:g>|<xliff:g id="country">南苏丹</xliff:g><xliff:g id="lat_lon">|4.847|31.595</xliff:g>"</string>
    <string name="C314" msgid="3840011425345102604">"J<xliff:g id="SEPARATOR">=</xliff:g>金斯敦<xliff:g id="TIMEZONE">|America/St_Vincent</xliff:g>|<xliff:g id="country">圣文森特和格林纳丁斯</xliff:g><xliff:g id="lat_lon">|13.156|-61.228</xliff:g>"</string>
    <string name="C315" msgid="8962557999110557329">"L<xliff:g id="SEPARATOR">=</xliff:g>利伯维尔<xliff:g id="TIMEZONE">|Africa/Libreville</xliff:g>|<xliff:g id="country">加蓬</xliff:g><xliff:g id="lat_lon">|0.39|9.454</xliff:g>"</string>
    <string name="C316" msgid="3674113287320887951">"L<xliff:g id="SEPARATOR">=</xliff:g>洛美<xliff:g id="TIMEZONE">|Africa/Lome</xliff:g>|<xliff:g id="country">多哥</xliff:g><xliff:g id="lat_lon">|6.13|1.216</xliff:g>"</string>
    <string name="C317" msgid="4818049429422081055">"L<xliff:g id="SEPARATOR">=</xliff:g>罗安达<xliff:g id="TIMEZONE">|Africa/Luanda</xliff:g>|<xliff:g id="country">安哥拉</xliff:g><xliff:g id="lat_lon">|-8.827|13.244</xliff:g>"</string>
    <string name="C318" msgid="3814107319819817789">"L<xliff:g id="SEPARATOR">=</xliff:g>卢萨卡<xliff:g id="TIMEZONE">|Africa/Lusaka</xliff:g>|<xliff:g id="country">赞比亚</xliff:g><xliff:g id="lat_lon">|-15.416|28.282</xliff:g>"</string>
    <string name="C319" msgid="5757039321992317631">"M<xliff:g id="SEPARATOR">=</xliff:g>马朱罗<xliff:g id="TIMEZONE">|Pacific/Majuro</xliff:g>|<xliff:g id="country">马绍尔群岛</xliff:g><xliff:g id="lat_lon">|7.091|171.382</xliff:g>"</string>
    <string name="C320" msgid="8334348266391215583">"M<xliff:g id="SEPARATOR">=</xliff:g>马拉博<xliff:g id="TIMEZONE">|Africa/Malabo</xliff:g>|<xliff:g id="country">赤道几内亚</xliff:g><xliff:g id="lat_lon">|3.753|8.78</xliff:g>"</string>
    <string name="C321" msgid="5401323973667971972">"M<xliff:g id="SEPARATOR">=</xliff:g>马普托<xliff:g id="TIMEZONE">|Africa/Maputo</xliff:g>|<xliff:g id="country">莫乘比克</xliff:g><xliff:g id="lat_lon">|-25.966|32.567</xliff:g>"</string>
    <string name="C322" msgid="67637052310417975">"M<xliff:g id="SEPARATOR">=</xliff:g>姆巴巴纳<xliff:g id="TIMEZONE">|Africa/Mbabane</xliff:g>|<xliff:g id="country">斯威士兰</xliff:g><xliff:g id="lat_lon">|-26.326|31.145</xliff:g>"</string>
    <string name="C323" msgid="4500721332684955521">"M<xliff:g id="SEPARATOR">=</xliff:g>莫罗尼<xliff:g id="TIMEZONE">|Indian/Comoro</xliff:g>|<xliff:g id="country">科摩罗</xliff:g><xliff:g id="lat_lon">|-11.693|43.254</xliff:g>"</string>
    <string name="C324" msgid="1741927819842539260">"E<xliff:g id="SEPARATOR">=</xliff:g>恩贾梅纳<xliff:g id="TIMEZONE">|Africa/Ndjamena</xliff:g>|<xliff:g id="country">乍得</xliff:g><xliff:g id="lat_lon">|12.119|15.05</xliff:g>"</string>
    <string name="C325" msgid="8771905307322194055">"E<xliff:g id="SEPARATOR">=</xliff:g>恩吉鲁穆德<xliff:g id="TIMEZONE">|Pacific/Palau</xliff:g>|<xliff:g id="country">太平洋岛国帕劳</xliff:g><xliff:g id="lat_lon">|7.501|134.624</xliff:g>"</string>
    <string name="C326" msgid="2389198042593603472">"N<xliff:g id="SEPARATOR">=</xliff:g>尼亚美<xliff:g id="TIMEZONE">|Africa/Niamey</xliff:g>|<xliff:g id="country">尼日尔</xliff:g><xliff:g id="lat_lon">|13.525|2.11</xliff:g>"</string>
    <string name="C327" msgid="5317479895686981912">"N<xliff:g id="SEPARATOR">=</xliff:g>尼科西亚<xliff:g id="TIMEZONE">|Europe/Nicosia</xliff:g>|<xliff:g id="country">塞浦路斯</xliff:g><xliff:g id="lat_lon">|35.045|33.051</xliff:g>"</string>
    <string name="C328" msgid="6416405203954996861">"N<xliff:g id="SEPARATOR">=</xliff:g>努瓦克肖特<xliff:g id="TIMEZONE">|Africa/Nouakchott</xliff:g>|<xliff:g id="country">毛里塔尼亚</xliff:g><xliff:g id="lat_lon">|18.079|-15.978</xliff:g>"</string>
    <string name="C329" msgid="6876960940903095843">"N<xliff:g id="SEPARATOR">=</xliff:g>努库阿洛法<xliff:g id="TIMEZONE">|Pacific/Tongatapu</xliff:g>|<xliff:g id="country">汤加</xliff:g><xliff:g id="lat_lon">|-21.134|-175.202</xliff:g>"</string>
    <string name="C330" msgid="1572294706542426161">"W<xliff:g id="SEPARATOR">=</xliff:g>瓦加杜古<xliff:g id="TIMEZONE">|Africa/Ouagadougou</xliff:g>|<xliff:g id="country">布基纳法索</xliff:g><xliff:g id="lat_lon">|12.368|-1.527</xliff:g>"</string>
    <string name="C331" msgid="2607492003890117689">"P<xliff:g id="SEPARATOR">=</xliff:g>帕利基尔<xliff:g id="TIMEZONE">|Pacific/Noumea</xliff:g>|<xliff:g id="country"></xliff:g><xliff:g id="lat_lon">|6.921|158.163</xliff:g>"</string>
    <string name="C332" msgid="8349533418456323370">"F<xliff:g id="SEPARATOR">=</xliff:g>菲利普斯堡<xliff:g id="TIMEZONE">|America/Lower_Princes</xliff:g>|<xliff:g id="country"></xliff:g><xliff:g id="lat_lon">|18.025|-63.048</xliff:g>"</string>
    <string name="C333" msgid="2842640664018042568">"B<xliff:g id="SEPARATOR">=</xliff:g>波德戈里察<xliff:g id="TIMEZONE">|Europe/Podgorica</xliff:g>|<xliff:g id="country">黑山</xliff:g><xliff:g id="lat_lon">|42.442|19.262</xliff:g>"</string>
    <string name="C334" msgid="3310146581437635671">"M<xliff:g id="SEPARATOR">=</xliff:g>莫尔兹比港<xliff:g id="TIMEZONE">|Pacific/Port_Moresby</xliff:g>|<xliff:g id="country">巴布亚新几内亚</xliff:g><xliff:g id="lat_lon">|-9.474|147.16</xliff:g>"</string>
    <string name="C335" msgid="3317158262102352303">"A<xliff:g id="SEPARATOR">=</xliff:g>埃法特岛<xliff:g id="TIMEZONE">|Pacific/Efate</xliff:g>|<xliff:g id="country"></xliff:g><xliff:g id="lat_lon">|-17.674|168.365</xliff:g>"</string>
    <string name="C336" msgid="3810072761869903472">"B<xliff:g id="SEPARATOR">=</xliff:g>波多诺伏<xliff:g id="TIMEZONE">|Africa/Porto-Novo</xliff:g>|<xliff:g id="country">贝宁</xliff:g><xliff:g id="lat_lon">|6.499|2.625</xliff:g>"</string>
    <string name="C337" msgid="3412269218104112252">"P<xliff:g id="SEPARATOR">=</xliff:g>普里什蒂纳<xliff:g id="TIMEZONE">|Europe/Belgrade</xliff:g>|<xliff:g id="country">塞尔维亚</xliff:g><xliff:g id="lat_lon">|42.664|21.164</xliff:g>"</string>
    <string name="C338" msgid="6151841959824325885">"L<xliff:g id="SEPARATOR">=</xliff:g>罗索<xliff:g id="TIMEZONE">|America/Dominica</xliff:g>|<xliff:g id="country">多米尼克</xliff:g><xliff:g id="lat_lon">|15.301|-61.388</xliff:g>"</string>
    <string name="C339" msgid="8909994815975646525">"T<xliff:g id="SEPARATOR">=</xliff:g>塔什干<xliff:g id="TIMEZONE">|Asia/Tashkent</xliff:g>|<xliff:g id="country">乌兹别克斯坦</xliff:g><xliff:g id="lat_lon">|41.312|69.279</xliff:g>"</string>
    <string name="C340" msgid="415479723070879485">"D<xliff:g id="SEPARATOR">=</xliff:g>第比利斯<xliff:g id="TIMEZONE">|Asia/Tbilisi</xliff:g>|<xliff:g id="country">格鲁吉亚</xliff:g><xliff:g id="lat_lon">|41.693|44.801</xliff:g>"</string>
    <string name="C341" msgid="2299478430610154042">"T<xliff:g id="SEPARATOR">=</xliff:g>廷布<xliff:g id="TIMEZONE">|Asia/Thimphu</xliff:g>|<xliff:g id="country">不丹</xliff:g><xliff:g id="lat_lon">|27.471|89.634</xliff:g>"</string>
    <string name="C342" msgid="7997617194333170685">"D<xliff:g id="SEPARATOR">=</xliff:g>地拉那<xliff:g id="TIMEZONE">|Europe/Tirane</xliff:g>|<xliff:g id="country">阿尔巴尼亚</xliff:g><xliff:g id="lat_lon">|41.328|19.819</xliff:g>"</string>
    <string name="C343" msgid="622805851462854910">"W<xliff:g id="SEPARATOR">=</xliff:g>瓦杜兹<xliff:g id="TIMEZONE">|Europe/Vaduz</xliff:g>|<xliff:g id="country">列支敦士登</xliff:g><xliff:g id="lat_lon">|47.139|9.523</xliff:g>"</string>
    <string name="C344" msgid="7629820826386244509">"W<xliff:g id="SEPARATOR">=</xliff:g>万象<xliff:g id="TIMEZONE">|Asia/Vientiane</xliff:g>|<xliff:g id="country">老挝</xliff:g><xliff:g id="lat_lon">|17.964|102.613</xliff:g>"</string>
    <string name="C345" msgid="1881198350378158072">"W<xliff:g id="SEPARATOR">=</xliff:g>温得和克<xliff:g id="TIMEZONE">|Africa/Windhoek</xliff:g>|<xliff:g id="country">纳米比亚</xliff:g><xliff:g id="lat_lon">|-22.574|17.079</xliff:g>"</string>
    <string name="C346" msgid="2947674392768816097">"Y<xliff:g id="SEPARATOR">=</xliff:g>雅温得<xliff:g id="TIMEZONE">|Africa/Douala</xliff:g>|<xliff:g id="country">喀麦隆</xliff:g><xliff:g id="lat_lon">|3.869|11.521</xliff:g>"</string>
    <string name="C347" msgid="6291282205599716861">"Y<xliff:g id="SEPARATOR">=</xliff:g>亚伦区<xliff:g id="TIMEZONE">|Pacific/Nauru</xliff:g>|<xliff:g id="country"></xliff:g><xliff:g id="lat_lon">|-0.547|166.916</xliff:g>"</string>
    <string name="C348" msgid="8462071023392592539">"A<xliff:g id="SEPARATOR">=</xliff:g>埃里温<xliff:g id="TIMEZONE">|Asia/Yerevan</xliff:g>|<xliff:g id="country">亚美尼亚</xliff:g><xliff:g id="lat_lon">|40.178|44.513</xliff:g>"</string>
    <!--add by xiaolei.huang  start-->
    <string name="C349">B<xliff:g id="separator">=</xliff:g>巴马科<xliff:g id="timezone">|Africa/Bamako</xliff:g>|<xliff:g id="country">马里</xliff:g><xliff:g id="lat_lon">|12.613|-7.985</xliff:g></string>
    <string name="C350">Y<xliff:g id="separator">=</xliff:g>亚穆苏克罗<xliff:g id="timezone">|Africa/Abidjan</xliff:g>|<xliff:g id="country">科特迪瓦</xliff:g><xliff:g id="lat_lon">|6.809|-5.273</xliff:g></string>
    <string name="C351">L<xliff:g id="separator">=</xliff:g>拉巴特<xliff:g id="timezone">|Africa/Casablanca</xliff:g>|<xliff:g id="country">摩洛哥</xliff:g><xliff:g id="lat_lon">|34.022|-6.835</xliff:g></string>
    <string name="C352">D<xliff:g id="separator">=</xliff:g>杜阿拉<xliff:g id="timezone">|Africa/Douala</xliff:g>|<xliff:g id="country">喀麦隆</xliff:g><xliff:g id="lat_lon">|4.054|9.664</xliff:g></string>
    <string name="C353">L<xliff:g id="separator">=</xliff:g>卢本巴希<xliff:g id="timezone">|Africa/Lubumbashi</xliff:g>|<xliff:g id="country">刚果民主共和国</xliff:g><xliff:g id="lat_lon">|-11.664|27.483</xliff:g></string>
    <string name="C354">L<xliff:g id="separator">=</xliff:g>利隆圭<xliff:g id="timezone">|Africa/Blantyre</xliff:g>|<xliff:g id="country">马拉维</xliff:g><xliff:g id="lat_lon">|-13.988|33.768</xliff:g></string>
    <string name="C355">D<xliff:g id="separator">=</xliff:g>多多马<xliff:g id="timezone">|Africa/Dar_es_Salaam</xliff:g>|<xliff:g id="country">坦桑尼亚</xliff:g><xliff:g id="lat_lon">|-6.179|35.747</xliff:g></string>
    <string name="C356">L<xliff:g id="separator">=</xliff:g>路易港<xliff:g id="timezone">|Indian/Mauritius</xliff:g>|<xliff:g id="country">毛里求斯</xliff:g><xliff:g id="lat_lon">|-20.162|57.503</xliff:g></string>
    <string name="C357">A<xliff:g id="separator">=</xliff:g>阿布扎比<xliff:g id="timezone">|Asia/Dubai</xliff:g>|<xliff:g id="country">阿拉伯联合酋长国</xliff:g><xliff:g id="lat_lon">|24.454|54.377</xliff:g></string>
    <string name="C358">J<xliff:g id="separator">=</xliff:g>加里宁格勒<xliff:g id="timezone">|Europe/Kaliningrad</xliff:g>|<xliff:g id="country">俄罗斯</xliff:g><xliff:g id="lat_lon">|54.71|20.511</xliff:g></string>
    <string name="C359">S<xliff:g id="separator">=</xliff:g>萨马拉<xliff:g id="timezone">|Europe/Samara</xliff:g>|<xliff:g id="country">俄罗斯</xliff:g><xliff:g id="lat_lon">|53.199|50.114</xliff:g></string>
    <string name="C360">Y<xliff:g id="separator">=</xliff:g>叶卡捷琳堡<xliff:g id="timezone">|Asia/Yekaterinburg</xliff:g>|<xliff:g id="country">俄罗斯</xliff:g><xliff:g id="lat_lon">|56.839|60.608</xliff:g></string>
    <string name="C361">E<xliff:g id="separator">=</xliff:g>鄂木斯克<xliff:g id="timezone">|Asia/Omsk</xliff:g>|<xliff:g id="country">俄罗斯</xliff:g><xliff:g id="lat_lon">|54.991|73.372</xliff:g></string>
    <string name="C362">K<xliff:g id="separator">=</xliff:g>克拉斯诺亚尔斯克<xliff:g id="timezone">|Asia/Krasnoyarsk</xliff:g>|<xliff:g id="country">俄罗斯</xliff:g><xliff:g id="lat_lon">|56.009|92.873</xliff:g></string>
    <string name="C363">Y<xliff:g id="separator">=</xliff:g>伊尔库茨克<xliff:g id="timezone">|Asia/Irkutsk</xliff:g>|<xliff:g id="country">俄罗斯</xliff:g><xliff:g id="lat_lon">|52.29|104.281</xliff:g></string>
    <string name="C364">Y<xliff:g id="separator">=</xliff:g>雅库茨克<xliff:g id="timezone">|Asia/Yakutsk</xliff:g>|<xliff:g id="country">伐罗斯</xliff:g><xliff:g id="lat_lon">|62.027|129.732</xliff:g></string>
    <string name="C365">H<xliff:g id="separator">=</xliff:g>海参崴<xliff:g id="timezone">|Asia/Vladivostok</xliff:g>|<xliff:g id="country">俄罗斯</xliff:g><xliff:g id="lat_lon">|43.115|131.886</xliff:g></string>
    <string name="C366">M<xliff:g id="separator">=</xliff:g>马加丹<xliff:g id="timezone">|Asia/Magadan</xliff:g>|<xliff:g id="country">伐罗斯</xliff:g><xliff:g id="lat_lon">|59.56|150.799</xliff:g></string>
    <string name="C367">K<xliff:g id="separator">=</xliff:g>堪察加半岛<xliff:g id="timezone">|Asia/Kamchatka</xliff:g>|<xliff:g id="country">俄罗斯</xliff:g><xliff:g id="lat_lon">|55.868|158.803</xliff:g></string>
    <string name="C368">J<xliff:g id="separator">=</xliff:g>基辅<xliff:g id="timezone">|Europe/Kiev</xliff:g>|<xliff:g id="country">乌克兰</xliff:g><xliff:g id="lat_lon">|50.45|30.524</xliff:g></string>
    <string name="C369">X<xliff:g id="separator">=</xliff:g>新西伯利亚<xliff:g id="timezone">|Asia/Novosibirsk</xliff:g>|<xliff:g id="country">俄罗斯</xliff:g><xliff:g id="lat_lon">|55.028|82.923</xliff:g></string>
    <string name="C370">C<xliff:g id="separator">=</xliff:g>赤塔市<xliff:g id="timezone">|Asia/Chita</xliff:g>|<xliff:g id="country">俄罗斯</xliff:g><xliff:g id="lat_lon">|52.033|113.501</xliff:g></string>
    <string name="C371">N<xliff:g id="separator">=</xliff:g>南萨哈林斯克<xliff:g id="timezone">|Asia/Sakhalin</xliff:g>|<xliff:g id="country">俄罗斯</xliff:g><xliff:g id="lat_lon">|46.957|142.727</xliff:g></string>
    <string name="C372">B<xliff:g id="separator">=</xliff:g>彼得罗巴浦洛夫斯克<xliff:g id="timezone">|Asia/Kamchatka</xliff:g>|<xliff:g id="country">俄罗斯</xliff:g><xliff:g id="lat_lon">|53.02|158.647</xliff:g></string>
    <string name="C373">A<xliff:g id="separator">=</xliff:g>阿斯塔纳<xliff:g id="timezone">|Asia/Almaty</xliff:g>|<xliff:g id="country">哈萨克斯坦</xliff:g><xliff:g id="lat_lon">|51.151|71.439</xliff:g></string>
    <string name="C374">T<xliff:g id="separator">=</xliff:g>塔拉瓦島<xliff:g id="timezone">|Pacific/Tarawa</xliff:g>|<xliff:g id="country">基里巴斯</xliff:g><xliff:g id="lat_lon">|1.485|172.969</xliff:g></string>
    <string name="C375">E<xliff:g id="separator">=</xliff:g>恩德伯里島<xliff:g id="timezone">|Pacific/Enderbury</xliff:g>|<xliff:g id="country">基里巴斯</xliff:g><xliff:g id="lat_lon">|-3.125|-171.086</xliff:g></string>
    <string name="C376">A<xliff:g id="separator">=</xliff:g>阿皮亚<xliff:g id="timezone">|Pacific/Apia</xliff:g>|<xliff:g id="country">萨摩亚</xliff:g><xliff:g id="lat_lon">|-13.834|-171.769</xliff:g></string>
</resources>
